{"parameters":{"count":110,"ids":["Param15","Param110","Param62","Param63","Param64","Param65","Param66","Param67","Param68","Param69","Param70","Param71","Param72","Param73","Param74","Param75","Param3","Param","Param2","Param4","Param5","Param6","Param7","Param8","Param9","Param10","Param11","Param12","Param13","Param14","Param16","Param17","Param18","Param19","Param20","Param21","Param22","Param23","Param24","Param25","Param26","Param27","Param28","Param29","Param30","Param31","Param32","Param33","Param34","Param35","Param36","Param37","Param38","Param39","Param40","Param41","Param42","Param43","Param44","Param45","Param46","Param47","Param48","Param49","Param50","Param51","Param52","Param53","Param54","Param55","Param56","Param57","Param58","Param59","Param60","Param61","Param76","Param77","Param78","Param79","Param80","Param81","Param82","Param83","Param84","Param85","Param86","Param87","Param88","Param89","Param90","Param91","Param92","Param93","Param94","Param95","Param96","Param97","Param98","Param99","Param100","Param101","Param102","Param103","Param104","Param105","Param106","Param107","Param108","Param109"],"minimumValues":{"0":0,"1":0,"2":0,"3":0,"4":0,"5":0,"6":0,"7":0,"8":0,"9":0,"10":0,"11":0,"12":0,"13":0,"14":0,"15":0,"16":0,"17":0,"18":0,"19":0,"20":0,"21":0,"22":0,"23":0,"24":0,"25":0,"26":0,"27":0,"28":0,"29":0,"30":0,"31":0,"32":0,"33":0,"34":0,"35":0,"36":0,"37":0,"38":0,"39":0,"40":0,"41":0,"42":0,"43":0,"44":0,"45":0,"46":0,"47":0,"48":0,"49":0,"50":0,"51":0,"52":0,"53":0,"54":0,"55":0,"56":0,"57":0,"58":0,"59":0,"60":0,"61":0,"62":0,"63":0,"64":0,"65":0,"66":0,"67":0,"68":0,"69":0,"70":0,"71":0,"72":0,"73":0,"74":0,"75":0,"76":0,"77":0,"78":0,"79":0,"80":0,"81":0,"82":0,"83":0,"84":0,"85":0,"86":0,"87":0,"88":0,"89":0,"90":0,"91":0,"92":0,"93":0,"94":0,"95":0,"96":0,"97":0,"98":0,"99":0,"100":0,"101":0,"102":0,"103":0,"104":0,"105":0,"106":0,"107":0,"108":0,"109":0},"maximumValues":{"0":1,"1":1,"2":1,"3":1,"4":1,"5":1,"6":1,"7":1,"8":1,"9":1,"10":1,"11":1,"12":1,"13":1,"14":1,"15":1,"16":1,"17":1,"18":1,"19":1,"20":1,"21":1,"22":1,"23":1,"24":1,"25":1,"26":1,"27":1,"28":1,"29":1,"30":1,"31":1,"32":1,"33":1,"34":1,"35":1,"36":1,"37":1,"38":1,"39":1,"40":1,"41":1,"42":1,"43":1,"44":1,"45":1,"46":1,"47":1,"48":1,"49":1,"50":1,"51":1,"52":1,"53":1,"54":1,"55":1,"56":1,"57":1,"58":1,"59":1,"60":1,"61":1,"62":1,"63":1,"64":1,"65":1,"66":1,"67":1,"68":1,"69":1,"70":1,"71":1,"72":1,"73":1,"74":1,"75":1,"76":1,"77":1,"78":1,"79":1,"80":1,"81":1,"82":1,"83":1,"84":1,"85":1,"86":1,"87":1,"88":1,"89":1,"90":1,"91":1,"92":1,"93":1,"94":1,"95":1,"96":1,"97":1,"98":1,"99":1,"100":1,"101":1,"102":1,"103":1,"104":1,"105":1,"106":1,"107":1,"108":1,"109":1},"defaultValues":{"0":0,"1":0,"2":0,"3":0,"4":0,"5":0,"6":0,"7":0,"8":0,"9":0,"10":0,"11":0,"12":0,"13":0,"14":0,"15":0,"16":0,"17":0,"18":0,"19":0,"20":0,"21":0,"22":0,"23":0,"24":0,"25":0,"26":0,"27":0,"28":0,"29":0,"30":0,"31":0,"32":0,"33":0,"34":0,"35":0,"36":0,"37":0,"38":0,"39":0,"40":0,"41":0,"42":0,"43":0,"44":0,"45":0,"46":0,"47":0,"48":0,"49":0,"50":0,"51":0,"52":0,"53":0,"54":0,"55":0,"56":0,"57":0,"58":0,"59":0,"60":0,"61":0,"62":0,"63":0,"64":0,"65":0,"66":0,"67":0,"68":0,"69":0,"70":0,"71":0,"72":0,"73":0,"74":0,"75":0,"76":0,"77":0,"78":0,"79":0,"80":0,"81":0,"82":0,"83":0,"84":0,"85":0,"86":0,"87":0,"88":0,"89":0,"90":0,"91":0,"92":0,"93":0,"94":0,"95":0,"96":0,"97":0,"98":0,"99":0,"100":0,"101":0,"102":0,"103":0,"104":0,"105":0,"106":0,"107":0,"108":0,"109":0},"values":{"0":0,"1":0,"2":0,"3":0,"4":0,"5":0,"6":0,"7":0,"8":0,"9":0,"10":0,"11":0,"12":0,"13":0,"14":0,"15":0,"16":0,"17":0,"18":0,"19":0,"20":0,"21":0,"22":0,"23":0,"24":0,"25":0,"26":0,"27":0,"28":0,"29":0,"30":0,"31":0,"32":0,"33":0,"34":0,"35":0,"36":0,"37":0,"38":0,"39":0,"40":0,"41":0,"42":0,"43":0,"44":0,"45":0,"46":0,"47":0,"48":0,"49":0,"50":0,"51":0,"52":0,"53":0,"54":0,"55":0,"56":0,"57":0,"58":0,"59":0,"60":0,"61":0,"62":0,"63":0,"64":0,"65":0,"66":0,"67":0,"68":0,"69":0,"70":0,"71":0,"72":0,"73":0,"74":0,"75":0,"76":0,"77":0,"78":0,"79":0,"80":0,"81":0,"82":0,"83":0,"84":0,"85":0,"86":0,"87":0,"88":0,"89":0,"90":0,"91":0,"92":0,"93":0,"94":0,"95":0,"96":0,"97":0,"98":0,"99":0,"100":0,"101":0,"102":0,"103":0,"104":0,"105":0,"106":0,"107":0,"108":0,"109":0}},"parts":{"count":2,"ids":["Part2","Part"],"opacities":{"0":1,"1":1}},"drawables":{"count":222,"ids":["ArtMesh110","ArtMesh112","ArtMesh115","ArtMesh117","ArtMesh116","ArtMesh119","ArtMesh118","ArtMesh121","ArtMesh120","ArtMesh123","ArtMesh122","ArtMesh125","ArtMesh124","ArtMesh127","ArtMesh126","ArtMesh129","ArtMesh128","ArtMesh131","ArtMesh130","ArtMesh133","ArtMesh132","ArtMesh136","ArtMesh135","ArtMesh138","ArtMesh137","ArtMesh140","ArtMesh139","ArtMesh141","ArtMesh143","ArtMesh142","ArtMesh145","ArtMesh144","ArtMesh147","ArtMesh146","ArtMesh149","ArtMesh148","ArtMesh151","ArtMesh150","ArtMesh153","ArtMesh152","ArtMesh155","ArtMesh154","ArtMesh157","ArtMesh156","ArtMesh159","ArtMesh158","ArtMesh161","ArtMesh160","ArtMesh163","ArtMesh162","ArtMesh165","ArtMesh164","ArtMesh167","ArtMesh166","ArtMesh168","ArtMesh169","ArtMesh170","ArtMesh171","ArtMesh172","ArtMesh173","ArtMesh174","ArtMesh175","ArtMesh176","ArtMesh177","ArtMesh178","ArtMesh179","ArtMesh180","ArtMesh181","ArtMesh182","ArtMesh184","ArtMesh183","ArtMesh186","ArtMesh185","ArtMesh188","ArtMesh187","ArtMesh190","ArtMesh189","ArtMesh192","ArtMesh191","ArtMesh194","ArtMesh193","ArtMesh196","ArtMesh195","ArtMesh198","ArtMesh197","ArtMesh200","ArtMesh199","ArtMesh202","ArtMesh201","ArtMesh204","ArtMesh203","ArtMesh206","ArtMesh205","ArtMesh208","ArtMesh207","ArtMesh210","ArtMesh209","ArtMesh212","ArtMesh211","ArtMesh214","ArtMesh213","ArtMesh216","ArtMesh215","ArtMesh218","ArtMesh217","ArtMesh220","ArtMesh219","ArtMesh222","ArtMesh221","ArtMesh224","ArtMesh223","ArtMesh226","ArtMesh225","ArtMesh228","ArtMesh227","ArtMesh230","ArtMesh229","ArtMesh232","ArtMesh231","ArtMesh234","ArtMesh233","ArtMesh236","ArtMesh235","ArtMesh238","ArtMesh237","ArtMesh240","ArtMesh239","ArtMesh242","ArtMesh241","ArtMesh244","ArtMesh243","ArtMesh246","ArtMesh245","ArtMesh248","ArtMesh247","ArtMesh250","ArtMesh249","ArtMesh252","ArtMesh251","ArtMesh254","ArtMesh253","ArtMesh256","ArtMesh255","ArtMesh258","ArtMesh257","ArtMesh260","ArtMesh259","ArtMesh262","ArtMesh261","ArtMesh264","ArtMesh263","ArtMesh266","ArtMesh265","ArtMesh268","ArtMesh267","ArtMesh270","ArtMesh269","ArtMesh272","ArtMesh271","ArtMesh274","ArtMesh273","ArtMesh278","ArtMesh277","ArtMesh280","ArtMesh279","ArtMesh282","ArtMesh281","ArtMesh284","ArtMesh283","ArtMesh286","ArtMesh285","ArtMesh288","ArtMesh287","ArtMesh290","ArtMesh289","ArtMesh292","ArtMesh291","ArtMesh294","ArtMesh293","ArtMesh296","ArtMesh295","ArtMesh298","ArtMesh297","ArtMesh300","ArtMesh299","ArtMesh302","ArtMesh301","ArtMesh304","ArtMesh303","ArtMesh306","ArtMesh305","ArtMesh308","ArtMesh307","ArtMesh310","ArtMesh309","ArtMesh312","ArtMesh311","ArtMesh314","ArtMesh313","ArtMesh315","ArtMesh317","ArtMesh316","ArtMesh111","ArtMesh99","ArtMesh35","ArtMesh34","ArtMesh33","ArtMesh32","ArtMesh31","ArtMesh30","ArtMesh29","ArtMesh28","ArtMesh27","ArtMesh26","ArtMesh25","ArtMesh24","ArtMesh23","ArtMesh22","ArtMesh13","ArtMesh2","ArtMesh","ArtMesh134"],"constantFlags":{"0":4,"1":4,"2":6,"3":4,"4":6,"5":4,"6":6,"7":4,"8":6,"9":4,"10":6,"11":4,"12":6,"13":4,"14":6,"15":4,"16":6,"17":4,"18":6,"19":4,"20":6,"21":4,"22":6,"23":4,"24":6,"25":4,"26":6,"27":6,"28":4,"29":6,"30":4,"31":6,"32":4,"33":6,"34":4,"35":6,"36":4,"37":6,"38":4,"39":6,"40":4,"41":6,"42":4,"43":6,"44":4,"45":6,"46":4,"47":6,"48":4,"49":6,"50":4,"51":6,"52":4,"53":6,"54":4,"55":4,"56":4,"57":4,"58":4,"59":4,"60":4,"61":4,"62":4,"63":4,"64":4,"65":4,"66":4,"67":4,"68":4,"69":4,"70":6,"71":4,"72":6,"73":4,"74":6,"75":4,"76":6,"77":4,"78":6,"79":4,"80":6,"81":4,"82":6,"83":4,"84":6,"85":4,"86":6,"87":4,"88":6,"89":4,"90":6,"91":4,"92":6,"93":4,"94":6,"95":4,"96":6,"97":4,"98":6,"99":4,"100":6,"101":4,"102":6,"103":4,"104":6,"105":4,"106":6,"107":4,"108":6,"109":4,"110":6,"111":4,"112":6,"113":4,"114":6,"115":4,"116":6,"117":4,"118":6,"119":4,"120":4,"121":4,"122":4,"123":4,"124":4,"125":4,"126":6,"127":4,"128":6,"129":4,"130":6,"131":4,"132":6,"133":4,"134":6,"135":4,"136":4,"137":4,"138":4,"139":4,"140":4,"141":4,"142":4,"143":4,"144":4,"145":4,"146":4,"147":4,"148":4,"149":4,"150":4,"151":4,"152":4,"153":4,"154":4,"155":4,"156":6,"157":4,"158":6,"159":4,"160":6,"161":4,"162":6,"163":4,"164":6,"165":4,"166":6,"167":4,"168":6,"169":4,"170":6,"171":4,"172":4,"173":4,"174":4,"175":4,"176":4,"177":4,"178":4,"179":4,"180":6,"181":4,"182":6,"183":4,"184":6,"185":4,"186":6,"187":4,"188":6,"189":4,"190":6,"191":4,"192":6,"193":4,"194":6,"195":4,"196":6,"197":4,"198":4,"199":4,"200":4,"201":6,"202":6,"203":4,"204":4,"205":4,"206":4,"207":4,"208":4,"209":4,"210":4,"211":4,"212":4,"213":4,"214":4,"215":4,"216":4,"217":4,"218":4,"219":4,"220":4,"221":4},"dynamicFlags":{"0":127,"1":127,"2":126,"3":127,"4":126,"5":127,"6":126,"7":127,"8":126,"9":127,"10":126,"11":127,"12":126,"13":127,"14":126,"15":127,"16":126,"17":127,"18":126,"19":127,"20":126,"21":127,"22":126,"23":127,"24":126,"25":127,"26":126,"27":126,"28":127,"29":126,"30":127,"31":126,"32":127,"33":126,"34":127,"35":126,"36":127,"37":126,"38":127,"39":126,"40":127,"41":126,"42":127,"43":126,"44":127,"45":126,"46":127,"47":126,"48":127,"49":126,"50":127,"51":126,"52":127,"53":126,"54":126,"55":126,"56":126,"57":127,"58":126,"59":126,"60":126,"61":126,"62":126,"63":126,"64":126,"65":126,"66":126,"67":126,"68":126,"69":127,"70":126,"71":127,"72":126,"73":127,"74":126,"75":127,"76":126,"77":127,"78":126,"79":127,"80":126,"81":127,"82":126,"83":127,"84":126,"85":127,"86":126,"87":127,"88":126,"89":127,"90":126,"91":127,"92":126,"93":127,"94":126,"95":127,"96":126,"97":127,"98":126,"99":127,"100":126,"101":127,"102":126,"103":127,"104":126,"105":127,"106":126,"107":127,"108":126,"109":127,"110":126,"111":127,"112":126,"113":127,"114":126,"115":127,"116":126,"117":127,"118":126,"119":127,"120":126,"121":127,"122":126,"123":127,"124":126,"125":127,"126":126,"127":127,"128":126,"129":127,"130":126,"131":127,"132":126,"133":127,"134":126,"135":127,"136":126,"137":127,"138":126,"139":127,"140":126,"141":127,"142":126,"143":127,"144":126,"145":127,"146":126,"147":127,"148":126,"149":127,"150":126,"151":127,"152":126,"153":127,"154":126,"155":127,"156":126,"157":127,"158":126,"159":127,"160":126,"161":127,"162":126,"163":127,"164":126,"165":127,"166":126,"167":127,"168":126,"169":127,"170":126,"171":127,"172":126,"173":127,"174":126,"175":127,"176":126,"177":127,"178":126,"179":127,"180":126,"181":127,"182":126,"183":127,"184":126,"185":127,"186":126,"187":127,"188":126,"189":127,"190":126,"191":127,"192":126,"193":127,"194":126,"195":127,"196":126,"197":127,"198":126,"199":126,"200":127,"201":126,"202":127,"203":127,"204":127,"205":127,"206":127,"207":127,"208":127,"209":127,"210":127,"211":127,"212":127,"213":127,"214":127,"215":127,"216":127,"217":127,"218":127,"219":127,"220":127,"221":127},"textureIndices":{"0":0,"1":0,"2":0,"3":0,"4":0,"5":0,"6":0,"7":0,"8":0,"9":0,"10":0,"11":0,"12":0,"13":0,"14":0,"15":0,"16":0,"17":0,"18":0,"19":0,"20":0,"21":0,"22":0,"23":0,"24":0,"25":0,"26":0,"27":0,"28":0,"29":0,"30":0,"31":0,"32":0,"33":0,"34":0,"35":0,"36":0,"37":0,"38":0,"39":0,"40":0,"41":0,"42":0,"43":0,"44":0,"45":0,"46":0,"47":0,"48":0,"49":0,"50":0,"51":0,"52":0,"53":0,"54":0,"55":0,"56":0,"57":0,"58":0,"59":0,"60":0,"61":0,"62":0,"63":0,"64":0,"65":0,"66":0,"67":0,"68":0,"69":0,"70":0,"71":0,"72":0,"73":0,"74":0,"75":0,"76":0,"77":0,"78":0,"79":0,"80":0,"81":0,"82":0,"83":0,"84":0,"85":0,"86":0,"87":0,"88":0,"89":0,"90":0,"91":0,"92":0,"93":0,"94":0,"95":0,"96":0,"97":0,"98":0,"99":0,"100":0,"101":0,"102":0,"103":0,"104":0,"105":0,"106":0,"107":0,"108":0,"109":0,"110":0,"111":0,"112":0,"113":0,"114":0,"115":0,"116":0,"117":0,"118":0,"119":0,"120":0,"121":0,"122":0,"123":0,"124":0,"125":0,"126":0,"127":0,"128":0,"129":0,"130":0,"131":0,"132":0,"133":0,"134":0,"135":0,"136":0,"137":0,"138":0,"139":0,"140":0,"141":0,"142":0,"143":0,"144":0,"145":0,"146":0,"147":0,"148":0,"149":0,"150":0,"151":0,"152":0,"153":0,"154":0,"155":0,"156":0,"157":0,"158":0,"159":0,"160":0,"161":0,"162":0,"163":0,"164":0,"165":0,"166":0,"167":0,"168":0,"169":0,"170":0,"171":0,"172":0,"173":0,"174":0,"175":0,"176":0,"177":0,"178":0,"179":0,"180":0,"181":0,"182":0,"183":0,"184":0,"185":0,"186":0,"187":0,"188":0,"189":0,"190":0,"191":0,"192":0,"193":0,"194":0,"195":0,"196":0,"197":0,"198":0,"199":0,"200":0,"201":0,"202":0,"203":0,"204":0,"205":0,"206":0,"207":0,"208":0,"209":0,"210":0,"211":0,"212":0,"213":0,"214":0,"215":0,"216":0,"217":0,"218":0,"219":0,"220":0,"221":0},"drawOrders":{"0":500,"1":500,"2":500,"3":500,"4":500,"5":500,"6":500,"7":500,"8":500,"9":500,"10":500,"11":500,"12":500,"13":500,"14":500,"15":500,"16":500,"17":500,"18":500,"19":500,"20":500,"21":500,"22":500,"23":500,"24":500,"25":500,"26":500,"27":500,"28":500,"29":500,"30":500,"31":500,"32":500,"33":500,"34":500,"35":500,"36":500,"37":500,"38":500,"39":500,"40":500,"41":500,"42":500,"43":500,"44":500,"45":500,"46":500,"47":500,"48":500,"49":500,"50":500,"51":500,"52":500,"53":500,"54":500,"55":500,"56":500,"57":500,"58":500,"59":500,"60":500,"61":500,"62":500,"63":500,"64":500,"65":500,"66":500,"67":500,"68":500,"69":500,"70":500,"71":500,"72":500,"73":500,"74":500,"75":500,"76":500,"77":500,"78":500,"79":500,"80":500,"81":500,"82":500,"83":500,"84":500,"85":500,"86":500,"87":500,"88":500,"89":500,"90":500,"91":500,"92":500,"93":500,"94":500,"95":500,"96":500,"97":500,"98":500,"99":500,"100":500,"101":500,"102":500,"103":500,"104":500,"105":500,"106":500,"107":500,"108":500,"109":500,"110":500,"111":500,"112":500,"113":500,"114":500,"115":500,"116":500,"117":500,"118":500,"119":500,"120":500,"121":500,"122":500,"123":500,"124":500,"125":500,"126":500,"127":500,"128":500,"129":500,"130":500,"131":500,"132":500,"133":500,"134":500,"135":500,"136":500,"137":500,"138":500,"139":500,"140":500,"141":500,"142":500,"143":500,"144":500,"145":500,"146":500,"147":500,"148":500,"149":500,"150":500,"151":500,"152":500,"153":500,"154":500,"155":500,"156":500,"157":500,"158":500,"159":500,"160":500,"161":500,"162":500,"163":500,"164":500,"165":500,"166":500,"167":500,"168":500,"169":500,"170":500,"171":500,"172":500,"173":500,"174":500,"175":500,"176":500,"177":500,"178":500,"179":500,"180":500,"181":500,"182":500,"183":500,"184":500,"185":500,"186":500,"187":500,"188":500,"189":500,"190":500,"191":500,"192":500,"193":500,"194":500,"195":500,"196":500,"197":500,"198":500,"199":500,"200":500,"201":500,"202":500,"203":500,"204":500,"205":500,"206":500,"207":500,"208":500,"209":500,"210":500,"211":500,"212":500,"213":500,"214":500,"215":500,"216":500,"217":500,"218":500,"219":500,"220":500,"221":500},"renderOrders":{"0":2,"1":0,"2":21,"3":22,"4":23,"5":24,"6":25,"7":26,"8":27,"9":28,"10":29,"11":30,"12":31,"13":32,"14":33,"15":34,"16":35,"17":36,"18":37,"19":38,"20":39,"21":40,"22":41,"23":42,"24":43,"25":44,"26":45,"27":46,"28":47,"29":48,"30":49,"31":50,"32":51,"33":52,"34":53,"35":54,"36":55,"37":56,"38":57,"39":58,"40":59,"41":60,"42":61,"43":62,"44":63,"45":64,"46":65,"47":66,"48":67,"49":68,"50":69,"51":70,"52":71,"53":72,"54":73,"55":74,"56":75,"57":76,"58":77,"59":78,"60":79,"61":80,"62":81,"63":82,"64":83,"65":84,"66":85,"67":86,"68":87,"69":88,"70":89,"71":90,"72":91,"73":92,"74":93,"75":94,"76":95,"77":96,"78":97,"79":98,"80":99,"81":100,"82":101,"83":102,"84":103,"85":104,"86":105,"87":106,"88":107,"89":108,"90":109,"91":110,"92":111,"93":112,"94":113,"95":114,"96":115,"97":116,"98":117,"99":118,"100":119,"101":120,"102":121,"103":122,"104":123,"105":124,"106":125,"107":126,"108":127,"109":128,"110":129,"111":130,"112":131,"113":132,"114":133,"115":134,"116":135,"117":136,"118":137,"119":138,"120":139,"121":140,"122":141,"123":142,"124":143,"125":144,"126":145,"127":146,"128":147,"129":148,"130":149,"131":150,"132":151,"133":152,"134":153,"135":154,"136":155,"137":156,"138":157,"139":158,"140":159,"141":160,"142":161,"143":162,"144":163,"145":164,"146":165,"147":166,"148":167,"149":168,"150":169,"151":170,"152":171,"153":172,"154":173,"155":174,"156":175,"157":176,"158":177,"159":178,"160":179,"161":180,"162":181,"163":182,"164":183,"165":184,"166":185,"167":186,"168":187,"169":188,"170":189,"171":190,"172":191,"173":192,"174":193,"175":194,"176":195,"177":196,"178":197,"179":198,"180":199,"181":200,"182":201,"183":202,"184":203,"185":204,"186":205,"187":206,"188":207,"189":208,"190":209,"191":210,"192":211,"193":212,"194":213,"195":214,"196":215,"197":216,"198":217,"199":218,"200":219,"201":220,"202":1,"203":3,"204":4,"205":5,"206":6,"207":7,"208":8,"209":9,"210":10,"211":11,"212":12,"213":13,"214":14,"215":15,"216":16,"217":17,"218":18,"219":19,"220":20,"221":221},"opacities":{"0":1,"1":1,"2":0,"3":1,"4":0,"5":1,"6":0,"7":1,"8":0,"9":1,"10":0,"11":1,"12":0,"13":1,"14":0,"15":1,"16":0,"17":1,"18":0,"19":1,"20":0,"21":1,"22":0,"23":1,"24":0,"25":1,"26":0,"27":0,"28":1,"29":0,"30":1,"31":0,"32":1,"33":0,"34":1,"35":0,"36":1,"37":0,"38":1,"39":0,"40":1,"41":0,"42":1,"43":0,"44":1,"45":0,"46":1,"47":0,"48":1,"49":0,"50":1,"51":0,"52":1,"53":0,"54":0,"55":0,"56":0,"57":0.029998779296875,"58":0,"59":0,"60":0,"61":0,"62":0,"63":0,"64":0,"65":0,"66":0,"67":0,"68":0,"69":1,"70":0,"71":1,"72":0,"73":1,"74":0,"75":1,"76":0,"77":1,"78":0,"79":1,"80":0,"81":1,"82":0,"83":1,"84":0,"85":1,"86":0,"87":1,"88":0,"89":1,"90":0,"91":1,"92":0,"93":1,"94":0,"95":1,"96":0,"97":1,"98":0,"99":1,"100":0,"101":1,"102":0,"103":1,"104":0,"105":1,"106":0,"107":1,"108":0,"109":1,"110":0,"111":1,"112":0,"113":1,"114":0,"115":1,"116":0,"117":1,"118":0,"119":0.81982421875,"120":0,"121":0.81982421875,"122":0,"123":0.81982421875,"124":0,"125":1,"126":0,"127":1,"128":0,"129":1,"130":0,"131":1,"132":0,"133":1,"134":0,"135":0.81982421875,"136":0,"137":0.81982421875,"138":0,"139":0.81982421875,"140":0,"141":0.81982421875,"142":0,"143":0.81982421875,"144":0,"145":0.81982421875,"146":0,"147":0.81982421875,"148":0,"149":0.81982421875,"150":0,"151":0.81982421875,"152":0,"153":0.81982421875,"154":0,"155":1,"156":0,"157":1,"158":0,"159":1,"160":0,"161":1,"162":0,"163":1,"164":0,"165":1,"166":0,"167":1,"168":0,"169":1,"170":0,"171":0.81982421875,"172":0,"173":0.81982421875,"174":0,"175":0.81982421875,"176":0,"177":0.81982421875,"178":0,"179":1,"180":0,"181":1,"182":0,"183":1,"184":0,"185":1,"186":0,"187":1,"188":0,"189":1,"190":0,"191":1,"192":0,"193":1,"194":0,"195":1,"196":0,"197":1,"198":0,"199":0,"200":1,"201":0,"202":0.63916015625,"203":1,"204":1,"205":1,"206":1,"207":1,"208":1,"209":1,"210":1,"211":1,"212":1,"213":1,"214":1,"215":1,"216":1,"217":1,"218":0.81982421875,"219":0.81982421875,"220":0.81982421875,"221":1},"maskCounts":{"0":0,"1":0,"2":0,"3":0,"4":0,"5":0,"6":0,"7":0,"8":0,"9":0,"10":0,"11":0,"12":0,"13":0,"14":0,"15":0,"16":0,"17":0,"18":0,"19":0,"20":0,"21":0,"22":0,"23":0,"24":0,"25":0,"26":0,"27":0,"28":0,"29":0,"30":0,"31":0,"32":0,"33":0,"34":0,"35":0,"36":0,"37":0,"38":0,"39":0,"40":0,"41":0,"42":0,"43":0,"44":0,"45":0,"46":0,"47":0,"48":0,"49":0,"50":0,"51":0,"52":0,"53":0,"54":0,"55":0,"56":0,"57":0,"58":0,"59":0,"60":0,"61":0,"62":0,"63":0,"64":0,"65":0,"66":0,"67":0,"68":0,"69":0,"70":0,"71":0,"72":0,"73":0,"74":0,"75":0,"76":0,"77":0,"78":0,"79":0,"80":0,"81":0,"82":0,"83":0,"84":0,"85":0,"86":0,"87":0,"88":0,"89":0,"90":0,"91":0,"92":0,"93":0,"94":0,"95":0,"96":0,"97":0,"98":0,"99":0,"100":0,"101":0,"102":0,"103":0,"104":0,"105":0,"106":0,"107":0,"108":0,"109":0,"110":0,"111":0,"112":0,"113":0,"114":0,"115":0,"116":0,"117":0,"118":0,"119":0,"120":0,"121":0,"122":0,"123":0,"124":0,"125":0,"126":0,"127":0,"128":0,"129":0,"130":0,"131":0,"132":0,"133":0,"134":0,"135":0,"136":0,"137":0,"138":0,"139":0,"140":0,"141":0,"142":0,"143":0,"144":0,"145":0,"146":0,"147":0,"148":0,"149":0,"150":0,"151":0,"152":0,"153":0,"154":0,"155":0,"156":0,"157":0,"158":0,"159":0,"160":0,"161":0,"162":0,"163":0,"164":0,"165":0,"166":0,"167":0,"168":0,"169":0,"170":0,"171":0,"172":0,"173":0,"174":0,"175":0,"176":0,"177":0,"178":0,"179":0,"180":0,"181":0,"182":0,"183":0,"184":0,"185":0,"186":0,"187":0,"188":0,"189":0,"190":0,"191":0,"192":0,"193":0,"194":0,"195":0,"196":0,"197":0,"198":0,"199":0,"200":0,"201":0,"202":0,"203":0,"204":0,"205":0,"206":0,"207":0,"208":0,"209":0,"210":0,"211":0,"212":0,"213":0,"214":0,"215":0,"216":0,"217":0,"218":0,"219":0,"220":0,"221":0},"masks":[{},{},{},{},{},{},{},{},{},{},{},{},{},{},{},{},{},{},{},{},{},{},{},{},{},{},{},{},{},{},{},{},{},{},{},{},{},{},{},{},{},{},{},{},{},{},{},{},{},{},{},{},{},{},{},{},{},{},{},{},{},{},{},{},{},{},{},{},{},{},{},{},{},{},{},{},{},{},{},{},{},{},{},{},{},{},{},{},{},{},{},{},{},{},{},{},{},{},{},{},{},{},{},{},{},{},{},{},{},{},{},{},{},{},{},{},{},{},{},{},{},{},{},{},{},{},{},{},{},{},{},{},{},{},{},{},{},{},{},{},{},{},{},{},{},{},{},{},{},{},{},{},{},{},{},{},{},{},{},{},{},{},{},{},{},{},{},{},{},{},{},{},{},{},{},{},{},{},{},{},{},{},{},{},{},{},{},{},{},{},{},{},{},{},{},{},{},{},{},{},{},{},{},{},{},{},{},{},{},{},{},{},{},{},{},{},{},{},{},{},{},{}],"vertexCounts":{"0":4,"1":4,"2":4,"3":4,"4":4,"5":4,"6":4,"7":4,"8":4,"9":4,"10":4,"11":4,"12":4,"13":4,"14":4,"15":4,"16":4,"17":4,"18":4,"19":4,"20":4,"21":4,"22":4,"23":4,"24":4,"25":4,"26":4,"27":4,"28":4,"29":4,"30":4,"31":4,"32":4,"33":4,"34":4,"35":4,"36":4,"37":4,"38":4,"39":4,"40":4,"41":4,"42":4,"43":4,"44":4,"45":4,"46":4,"47":4,"48":4,"49":4,"50":4,"51":4,"52":4,"53":4,"54":4,"55":4,"56":4,"57":4,"58":4,"59":4,"60":4,"61":4,"62":4,"63":4,"64":4,"65":4,"66":4,"67":4,"68":4,"69":4,"70":4,"71":4,"72":4,"73":4,"74":4,"75":4,"76":4,"77":4,"78":4,"79":4,"80":4,"81":4,"82":4,"83":4,"84":4,"85":4,"86":4,"87":4,"88":4,"89":4,"90":4,"91":4,"92":4,"93":4,"94":4,"95":4,"96":4,"97":4,"98":4,"99":4,"100":4,"101":4,"102":4,"103":4,"104":4,"105":4,"106":4,"107":4,"108":4,"109":4,"110":4,"111":4,"112":4,"113":4,"114":4,"115":4,"116":4,"117":4,"118":4,"119":4,"120":4,"121":4,"122":4,"123":4,"124":4,"125":4,"126":4,"127":4,"128":4,"129":4,"130":4,"131":4,"132":4,"133":4,"134":4,"135":4,"136":4,"137":4,"138":4,"139":4,"140":4,"141":4,"142":4,"143":4,"144":4,"145":4,"146":4,"147":4,"148":4,"149":4,"150":4,"151":4,"152":4,"153":4,"154":4,"155":4,"156":4,"157":4,"158":4,"159":4,"160":4,"161":4,"162":4,"163":4,"164":4,"165":4,"166":4,"167":4,"168":4,"169":4,"170":4,"171":4,"172":4,"173":4,"174":4,"175":4,"176":4,"177":4,"178":4,"179":4,"180":4,"181":4,"182":4,"183":4,"184":4,"185":4,"186":4,"187":4,"188":4,"189":4,"190":4,"191":4,"192":4,"193":4,"194":4,"195":4,"196":4,"197":4,"198":4,"199":4,"200":4,"201":4,"202":4,"203":4,"204":4,"205":4,"206":4,"207":4,"208":4,"209":4,"210":4,"211":4,"212":4,"213":4,"214":4,"215":4,"216":4,"217":4,"218":4,"219":4,"220":4,"221":4},"vertexPositions":[{"0":0.308837890625,"1":0.048736572265625,"2":0.263671875,"3":0.048736572265625,"4":0.308837890625,"5":0.00749969482421875,"6":0.263671875,"7":0.00749969482421875},{"0":0.60986328125,"1":0.2237548828125,"2":-0.607421875,"3":0.2237548828125,"4":0.60986328125,"5":-0.11376953125,"6":-0.607421875,"7":-0.11376953125},{"0":-0.5517578125,"1":0.15673828125,"2":-0.5966796875,"3":0.15673828125,"4":-0.5517578125,"5":0.11553955078125,"6":-0.5966796875,"7":0.11553955078125},{"0":-0.492431640625,"1":0.1624755859375,"2":-0.54736328125,"3":0.1624755859375,"4":-0.492431640625,"5":0.10247802734375,"6":-0.54736328125,"7":0.10247802734375},{"0":-0.498046875,"1":0.15673828125,"2":-0.54296875,"3":0.15673828125,"4":-0.498046875,"5":0.11553955078125,"6":-0.54296875,"7":0.11553955078125},{"0":-0.4375,"1":0.1624755859375,"2":-0.492431640625,"3":0.1624755859375,"4":-0.4375,"5":0.10247802734375,"6":-0.492431640625,"7":0.10247802734375},{"0":-0.44287109375,"1":0.15673828125,"2":-0.48779296875,"3":0.15673828125,"4":-0.44287109375,"5":0.11553955078125,"6":-0.48779296875,"7":0.11553955078125},{"0":-0.384033203125,"1":0.1624755859375,"2":-0.43896484375,"3":0.1624755859375,"4":-0.384033203125,"5":0.10247802734375,"6":-0.43896484375,"7":0.10247802734375},{"0":-0.389404296875,"1":0.15673828125,"2":-0.4345703125,"3":0.15673828125,"4":-0.389404296875,"5":0.11553955078125,"6":-0.4345703125,"7":0.11553955078125},{"0":-0.327880859375,"1":0.1624755859375,"2":-0.3828125,"3":0.1624755859375,"4":-0.327880859375,"5":0.10247802734375,"6":-0.3828125,"7":0.10247802734375},{"0":-0.333251953125,"1":0.15673828125,"2":-0.37841796875,"3":0.15673828125,"4":-0.333251953125,"5":0.11553955078125,"6":-0.37841796875,"7":0.11553955078125},{"0":-0.2734375,"1":0.1624755859375,"2":-0.328369140625,"3":0.1624755859375,"4":-0.2734375,"5":0.10247802734375,"6":-0.328369140625,"7":0.10247802734375},{"0":-0.27880859375,"1":0.15673828125,"2":-0.323974609375,"3":0.15673828125,"4":-0.27880859375,"5":0.11553955078125,"6":-0.323974609375,"7":0.11553955078125},{"0":-0.2183837890625,"1":0.1624755859375,"2":-0.2734375,"3":0.1624755859375,"4":-0.2183837890625,"5":0.10247802734375,"6":-0.2734375,"7":0.10247802734375},{"0":-0.223876953125,"1":0.15673828125,"2":-0.268798828125,"3":0.15673828125,"4":-0.223876953125,"5":0.11553955078125,"6":-0.268798828125,"7":0.11553955078125},{"0":-0.16357421875,"1":0.1624755859375,"2":-0.2186279296875,"3":0.1624755859375,"4":-0.16357421875,"5":0.10247802734375,"6":-0.2186279296875,"7":0.10247802734375},{"0":-0.1690673828125,"1":0.15673828125,"2":-0.2139892578125,"3":0.15673828125,"4":-0.1690673828125,"5":0.11553955078125,"6":-0.2139892578125,"7":0.11553955078125},{"0":-0.1099853515625,"1":0.1624755859375,"2":-0.1649169921875,"3":0.1624755859375,"4":-0.1099853515625,"5":0.10247802734375,"6":-0.1649169921875,"7":0.10247802734375},{"0":-0.11541748046875,"1":0.15673828125,"2":-0.160400390625,"3":0.15673828125,"4":-0.11541748046875,"5":0.11553955078125,"6":-0.160400390625,"7":0.11553955078125},{"0":-0.053558349609375,"1":0.1624755859375,"2":-0.10858154296875,"3":0.1624755859375,"4":-0.053558349609375,"5":0.1024169921875,"6":-0.10858154296875,"7":0.1024169921875},{"0":-0.05902099609375,"1":0.15673828125,"2":-0.10400390625,"3":0.15673828125,"4":-0.05902099609375,"5":0.115478515625,"6":-0.10400390625,"7":0.115478515625},{"0":0.00045371055603027344,"1":0.1624755859375,"2":-0.054534912109375,"3":0.1624755859375,"4":0.00045371055603027344,"5":0.1024169921875,"6":-0.054534912109375,"7":0.1024169921875},{"0":-0.004993438720703125,"1":0.15673828125,"2":-0.04998779296875,"3":0.15673828125,"4":-0.004993438720703125,"5":0.115478515625,"6":-0.04998779296875,"7":0.115478515625},{"0":0.055328369140625,"1":0.1624755859375,"2":0.0003216266632080078,"3":0.1624755859375,"4":0.055328369140625,"5":0.1024169921875,"6":0.0003216266632080078,"7":0.1024169921875},{"0":0.04986572265625,"1":0.15673828125,"2":0.00487518310546875,"3":0.15673828125,"4":0.04986572265625,"5":0.115478515625,"6":0.00487518310546875,"7":0.115478515625},{"0":0.1112060546875,"1":0.1624755859375,"2":0.05621337890625,"3":0.1624755859375,"4":0.1112060546875,"5":0.1024169921875,"6":0.05621337890625,"7":0.1024169921875},{"0":0.10577392578125,"1":0.15673828125,"2":0.060791015625,"3":0.15673828125,"4":0.10577392578125,"5":0.115478515625,"6":0.060791015625,"7":0.115478515625},{"0":0.1756591796875,"1":0.15673828125,"2":0.130615234375,"3":0.15673828125,"4":0.1756591796875,"5":0.115478515625,"6":0.130615234375,"7":0.115478515625},{"0":-0.46533203125,"1":0.10797119140625,"2":-0.52001953125,"3":0.10797119140625,"4":-0.46533203125,"5":0.0479736328125,"6":-0.52001953125,"7":0.0479736328125},{"0":-0.470703125,"1":0.10223388671875,"2":-0.515625,"3":0.10223388671875,"4":-0.470703125,"5":0.061004638671875,"6":-0.515625,"7":0.061004638671875},{"0":-0.41015625,"1":0.10797119140625,"2":-0.465087890625,"3":0.10797119140625,"4":-0.41015625,"5":0.0479736328125,"6":-0.465087890625,"7":0.0479736328125},{"0":-0.41552734375,"1":0.10223388671875,"2":-0.46044921875,"3":0.10223388671875,"4":-0.41552734375,"5":0.061004638671875,"6":-0.46044921875,"7":0.061004638671875},{"0":-0.356201171875,"1":0.10797119140625,"2":-0.4111328125,"3":0.10797119140625,"4":-0.356201171875,"5":0.0479736328125,"6":-0.4111328125,"7":0.0479736328125},{"0":-0.361572265625,"1":0.10223388671875,"2":-0.406494140625,"3":0.10223388671875,"4":-0.361572265625,"5":0.061004638671875,"6":-0.406494140625,"7":0.061004638671875},{"0":-0.2998046875,"1":0.10797119140625,"2":-0.35498046875,"3":0.10797119140625,"4":-0.2998046875,"5":0.0479736328125,"6":-0.35498046875,"7":0.0479736328125},{"0":-0.305419921875,"1":0.10223388671875,"2":-0.350341796875,"3":0.10223388671875,"4":-0.305419921875,"5":0.061004638671875,"6":-0.350341796875,"7":0.061004638671875},{"0":-0.2464599609375,"1":0.10797119140625,"2":-0.301513671875,"3":0.10797119140625,"4":-0.2464599609375,"5":0.0479736328125,"6":-0.301513671875,"7":0.0479736328125},{"0":-0.251953125,"1":0.10223388671875,"2":-0.296875,"3":0.10223388671875,"4":-0.251953125,"5":0.061004638671875,"6":-0.296875,"7":0.061004638671875},{"0":-0.1900634765625,"1":0.10797119140625,"2":-0.2449951171875,"3":0.10797119140625,"4":-0.1900634765625,"5":0.0479736328125,"6":-0.2449951171875,"7":0.0479736328125},{"0":-0.195556640625,"1":0.10223388671875,"2":-0.240478515625,"3":0.10223388671875,"4":-0.195556640625,"5":0.061004638671875,"6":-0.240478515625,"7":0.061004638671875},{"0":-0.13623046875,"1":0.10797119140625,"2":-0.1912841796875,"3":0.10797119140625,"4":-0.13623046875,"5":0.0479736328125,"6":-0.1912841796875,"7":0.0479736328125},{"0":-0.1417236328125,"1":0.10223388671875,"2":-0.1866455078125,"3":0.10223388671875,"4":-0.1417236328125,"5":0.061004638671875,"6":-0.1866455078125,"7":0.061004638671875},{"0":-0.08282470703125,"1":0.10797119140625,"2":-0.1378173828125,"3":0.10797119140625,"4":-0.08282470703125,"5":0.0479736328125,"6":-0.1378173828125,"7":0.0479736328125},{"0":-0.0882568359375,"1":0.10223388671875,"2":-0.13330078125,"3":0.10223388671875,"4":-0.0882568359375,"5":0.061004638671875,"6":-0.13330078125,"7":0.061004638671875},{"0":-0.02783203125,"1":0.10797119140625,"2":-0.08282470703125,"3":0.10797119140625,"4":-0.02783203125,"5":0.0479736328125,"6":-0.08282470703125,"7":0.0479736328125},{"0":-0.03326416015625,"1":0.10223388671875,"2":-0.0782470703125,"3":0.10223388671875,"4":-0.03326416015625,"5":0.061004638671875,"6":-0.0782470703125,"7":0.061004638671875},{"0":0.02716064453125,"1":0.10797119140625,"2":-0.02783203125,"3":0.10797119140625,"4":0.02716064453125,"5":0.0479736328125,"6":-0.02783203125,"7":0.0479736328125},{"0":0.0217132568359375,"1":0.10223388671875,"2":-0.023284912109375,"3":0.10223388671875,"4":0.0217132568359375,"5":0.061004638671875,"6":-0.023284912109375,"7":0.061004638671875},{"0":0.0836181640625,"1":0.10797119140625,"2":0.02862548828125,"3":0.10797119140625,"4":0.0836181640625,"5":0.0479736328125,"6":0.02862548828125,"7":0.0479736328125},{"0":0.07818603515625,"1":0.10223388671875,"2":0.033172607421875,"3":0.10223388671875,"4":0.07818603515625,"5":0.061004638671875,"6":0.033172607421875,"7":0.061004638671875},{"0":0.1385498046875,"1":0.10797119140625,"2":0.08355712890625,"3":0.10797119140625,"4":0.1385498046875,"5":0.0479736328125,"6":0.08355712890625,"7":0.0479736328125},{"0":0.133056640625,"1":0.10223388671875,"2":0.088134765625,"3":0.10223388671875,"4":0.133056640625,"5":0.061004638671875,"6":0.088134765625,"7":0.061004638671875},{"0":0.192138671875,"1":0.10797119140625,"2":0.1370849609375,"3":0.10797119140625,"4":0.192138671875,"5":0.0479736328125,"6":0.1370849609375,"7":0.0479736328125},{"0":0.1866455078125,"1":0.10223388671875,"2":0.1417236328125,"3":0.10223388671875,"4":0.1866455078125,"5":0.061004638671875,"6":0.1417236328125,"7":0.061004638671875},{"0":-0.53076171875,"1":0.048736572265625,"2":-0.576171875,"3":0.048736572265625,"4":-0.53076171875,"5":0.00749969482421875,"6":-0.576171875,"7":0.00749969482421875},{"0":-0.53759765625,"1":0.1031494140625,"2":-0.58251953125,"3":0.1031494140625,"4":-0.53759765625,"5":0.0618896484375,"6":-0.58251953125,"7":0.0618896484375},{"0":-0.51953125,"1":-0.00017499923706054688,"2":-0.564453125,"3":-0.00017499923706054688,"4":-0.51953125,"5":-0.041412353515625,"6":-0.564453125,"7":-0.041412353515625},{"0":-0.53759765625,"1":-0.056549072265625,"2":-0.58251953125,"3":-0.056549072265625,"4":-0.53759765625,"5":-0.0977783203125,"6":-0.58251953125,"7":-0.0977783203125},{"0":-0.464111328125,"1":-0.056549072265625,"2":-0.50927734375,"3":-0.056549072265625,"4":-0.464111328125,"5":-0.0977783203125,"6":-0.50927734375,"7":-0.0977783203125},{"0":-0.387451171875,"1":-0.056549072265625,"2":-0.4326171875,"3":-0.056549072265625,"4":-0.387451171875,"5":-0.0977783203125,"6":-0.4326171875,"7":-0.0977783203125},{"0":-0.18115234375,"1":-0.056549072265625,"2":-0.2261962890625,"3":-0.056549072265625,"4":-0.18115234375,"5":-0.0977783203125,"6":-0.2261962890625,"7":-0.0977783203125},{"0":0.0233612060546875,"1":-0.056549072265625,"2":-0.021636962890625,"3":-0.056549072265625,"4":0.0233612060546875,"5":-0.0977783203125,"6":-0.021636962890625,"7":-0.0977783203125},{"0":0.09893798828125,"1":-0.056549072265625,"2":0.053924560546875,"3":-0.056549072265625,"4":0.09893798828125,"5":-0.0977783203125,"6":0.053924560546875,"7":-0.0977783203125},{"0":0.1741943359375,"1":-0.056549072265625,"2":0.129150390625,"3":-0.056549072265625,"4":0.1741943359375,"5":-0.0977783203125,"6":0.129150390625,"7":-0.0977783203125},{"0":0.155029296875,"1":-0.002132415771484375,"2":0.11004638671875,"3":-0.002132415771484375,"4":0.155029296875,"5":-0.04339599609375,"6":0.11004638671875,"7":-0.04339599609375},{"0":0.1683349609375,"1":0.050323486328125,"2":0.12335205078125,"3":0.050323486328125,"4":0.1683349609375,"5":0.009063720703125,"6":0.12335205078125,"7":0.009063720703125},{"0":0.59423828125,"1":-0.0308685302734375,"2":0.54931640625,"3":-0.0308685302734375,"4":0.59423828125,"5":-0.0721435546875,"6":0.54931640625,"7":-0.0721435546875},{"0":-0.5390625,"1":0.2105712890625,"2":-0.583984375,"3":0.2105712890625,"4":-0.5390625,"5":0.1693115234375,"6":-0.583984375,"7":0.1693115234375},{"0":-0.25146484375,"1":0.2099609375,"2":-0.29638671875,"3":0.2099609375,"4":-0.25146484375,"5":0.168701171875,"6":-0.29638671875,"7":0.168701171875},{"0":-0.451171875,"1":0.05535888671875,"2":-0.50634765625,"3":0.05535888671875,"4":-0.451171875,"5":-0.00464630126953125,"6":-0.50634765625,"7":-0.00464630126953125},{"0":-0.45654296875,"1":0.04962158203125,"2":-0.50146484375,"3":0.04962158203125,"4":-0.45654296875,"5":0.0083770751953125,"6":-0.50146484375,"7":0.0083770751953125},{"0":-0.397705078125,"1":0.05535888671875,"2":-0.45263671875,"3":0.05535888671875,"4":-0.397705078125,"5":-0.00464630126953125,"6":-0.45263671875,"7":-0.00464630126953125},{"0":-0.403076171875,"1":0.04962158203125,"2":-0.447998046875,"3":0.04962158203125,"4":-0.403076171875,"5":0.0083770751953125,"6":-0.447998046875,"7":0.0083770751953125},{"0":-0.34228515625,"1":0.05535888671875,"2":-0.397216796875,"3":0.05535888671875,"4":-0.34228515625,"5":-0.00464630126953125,"6":-0.397216796875,"7":-0.00464630126953125},{"0":-0.34765625,"1":0.04962158203125,"2":-0.392822265625,"3":0.04962158203125,"4":-0.34765625,"5":0.0083770751953125,"6":-0.392822265625,"7":0.0083770751953125},{"0":-0.28857421875,"1":0.05535888671875,"2":-0.343505859375,"3":0.05535888671875,"4":-0.28857421875,"5":-0.00464630126953125,"6":-0.343505859375,"7":-0.00464630126953125},{"0":-0.2939453125,"1":0.04962158203125,"2":-0.3388671875,"3":0.04962158203125,"4":-0.2939453125,"5":0.0083770751953125,"6":-0.3388671875,"7":0.0083770751953125},{"0":-0.232177734375,"1":0.05535888671875,"2":-0.287109375,"3":0.05535888671875,"4":-0.232177734375,"5":-0.00464630126953125,"6":-0.287109375,"7":-0.00464630126953125},{"0":-0.237548828125,"1":0.04962158203125,"2":-0.282470703125,"3":0.04962158203125,"4":-0.237548828125,"5":0.0083770751953125,"6":-0.282470703125,"7":0.0083770751953125},{"0":-0.1771240234375,"1":0.05535888671875,"2":-0.232177734375,"3":0.05535888671875,"4":-0.1771240234375,"5":-0.00464630126953125,"6":-0.232177734375,"7":-0.00464630126953125},{"0":-0.1826171875,"1":0.04962158203125,"2":-0.2276611328125,"3":0.04962158203125,"4":-0.1826171875,"5":0.0083770751953125,"6":-0.2276611328125,"7":0.0083770751953125},{"0":-0.1212158203125,"1":0.05535888671875,"2":-0.1761474609375,"3":0.05535888671875,"4":-0.1212158203125,"5":-0.00464630126953125,"6":-0.1761474609375,"7":-0.00464630126953125},{"0":-0.126708984375,"1":0.04962158203125,"2":-0.171630859375,"3":0.04962158203125,"4":-0.126708984375,"5":0.0083770751953125,"6":-0.171630859375,"7":0.0083770751953125},{"0":-0.066162109375,"1":0.05535888671875,"2":-0.12115478515625,"3":0.05535888671875,"4":-0.066162109375,"5":-0.00464630126953125,"6":-0.12115478515625,"7":-0.00464630126953125},{"0":-0.07159423828125,"1":0.04962158203125,"2":-0.11663818359375,"3":0.04962158203125,"4":-0.07159423828125,"5":0.0083770751953125,"6":-0.11663818359375,"7":0.0083770751953125},{"0":-0.0126190185546875,"1":0.05535888671875,"2":-0.067626953125,"3":0.05535888671875,"4":-0.0126190185546875,"5":-0.00464630126953125,"6":-0.067626953125,"7":-0.00464630126953125},{"0":-0.01806640625,"1":0.04962158203125,"2":-0.06304931640625,"3":0.04962158203125,"4":-0.01806640625,"5":0.0083770751953125,"6":-0.06304931640625,"7":0.0083770751953125},{"0":0.041107177734375,"1":0.05535888671875,"2":-0.01389312744140625,"3":0.05535888671875,"4":0.041107177734375,"5":-0.00464630126953125,"6":-0.01389312744140625,"7":-0.00464630126953125},{"0":0.03564453125,"1":0.04962158203125,"2":-0.00934600830078125,"3":0.04962158203125,"4":0.03564453125,"5":0.0083770751953125,"6":-0.00934600830078125,"7":0.0083770751953125},{"0":0.09912109375,"1":0.05535888671875,"2":0.04412841796875,"3":0.05535888671875,"4":0.09912109375,"5":-0.00464630126953125,"6":0.04412841796875,"7":-0.00464630126953125},{"0":0.09368896484375,"1":0.04962158203125,"2":0.048675537109375,"3":0.04962158203125,"4":0.09368896484375,"5":0.0083770751953125,"6":0.048675537109375,"7":0.0083770751953125},{"0":-0.4228515625,"1":0.003940582275390625,"2":-0.477783203125,"3":0.003940582275390625,"4":-0.4228515625,"5":-0.056060791015625,"6":-0.477783203125,"7":-0.056060791015625},{"0":-0.42822265625,"1":-0.0017843246459960938,"2":-0.47314453125,"3":-0.0017843246459960938,"4":-0.42822265625,"5":-0.04302978515625,"6":-0.47314453125,"7":-0.04302978515625},{"0":-0.36767578125,"1":0.003940582275390625,"2":-0.4228515625,"3":0.003940582275390625,"4":-0.36767578125,"5":-0.056060791015625,"6":-0.4228515625,"7":-0.056060791015625},{"0":-0.373291015625,"1":-0.0017843246459960938,"2":-0.418212890625,"3":-0.0017843246459960938,"4":-0.373291015625,"5":-0.04302978515625,"6":-0.418212890625,"7":-0.04302978515625},{"0":-0.3125,"1":0.003940582275390625,"2":-0.36767578125,"3":0.003940582275390625,"4":-0.3125,"5":-0.056060791015625,"6":-0.36767578125,"7":-0.056060791015625},{"0":-0.318115234375,"1":-0.0017843246459960938,"2":-0.363037109375,"3":-0.0017843246459960938,"4":-0.318115234375,"5":-0.04302978515625,"6":-0.363037109375,"7":-0.04302978515625},{"0":-0.258544921875,"1":0.003940582275390625,"2":-0.3134765625,"3":0.003940582275390625,"4":-0.258544921875,"5":-0.056060791015625,"6":-0.3134765625,"7":-0.056060791015625},{"0":-0.263916015625,"1":-0.0017843246459960938,"2":-0.30908203125,"3":-0.0017843246459960938,"4":-0.263916015625,"5":-0.04302978515625,"6":-0.30908203125,"7":-0.04302978515625},{"0":-0.2037353515625,"1":0.003940582275390625,"2":-0.2587890625,"3":0.003940582275390625,"4":-0.2037353515625,"5":-0.056060791015625,"6":-0.2587890625,"7":-0.056060791015625},{"0":-0.209228515625,"1":-0.0017843246459960938,"2":-0.254150390625,"3":-0.0017843246459960938,"4":-0.209228515625,"5":-0.04302978515625,"6":-0.254150390625,"7":-0.04302978515625},{"0":-0.1488037109375,"1":0.003940582275390625,"2":-0.203857421875,"3":0.003940582275390625,"4":-0.1488037109375,"5":-0.056060791015625,"6":-0.203857421875,"7":-0.056060791015625},{"0":-0.154296875,"1":-0.0017843246459960938,"2":-0.19921875,"3":-0.0017843246459960938,"4":-0.154296875,"5":-0.04302978515625,"6":-0.19921875,"7":-0.04302978515625},{"0":-0.0947265625,"1":0.003940582275390625,"2":-0.1497802734375,"3":0.003940582275390625,"4":-0.0947265625,"5":-0.056060791015625,"6":-0.1497802734375,"7":-0.056060791015625},{"0":-0.10015869140625,"1":-0.0017843246459960938,"2":-0.1451416015625,"3":-0.0017843246459960938,"4":-0.10015869140625,"5":-0.04302978515625,"6":-0.1451416015625,"7":-0.04302978515625},{"0":-0.038665771484375,"1":0.003940582275390625,"2":-0.09368896484375,"3":0.003940582275390625,"4":-0.038665771484375,"5":-0.056060791015625,"6":-0.09368896484375,"7":-0.056060791015625},{"0":-0.04412841796875,"1":-0.0017843246459960938,"2":-0.089111328125,"3":-0.0017843246459960938,"4":-0.04412841796875,"5":-0.04302978515625,"6":-0.089111328125,"7":-0.04302978515625},{"0":0.0151519775390625,"1":0.003940582275390625,"2":-0.03985595703125,"3":0.003940582275390625,"4":0.0151519775390625,"5":-0.056060791015625,"6":-0.03985595703125,"7":-0.056060791015625},{"0":0.00970458984375,"1":-0.0017843246459960938,"2":-0.035308837890625,"3":-0.0017843246459960938,"4":0.00970458984375,"5":-0.04302978515625,"6":-0.035308837890625,"7":-0.04302978515625},{"0":0.0711669921875,"1":0.003940582275390625,"2":0.0161895751953125,"3":0.003940582275390625,"4":0.0711669921875,"5":-0.056060791015625,"6":0.0161895751953125,"7":-0.056060791015625},{"0":0.06573486328125,"1":-0.0017843246459960938,"2":0.020751953125,"3":-0.0017843246459960938,"4":0.06573486328125,"5":-0.04302978515625,"6":0.020751953125,"7":-0.04302978515625},{"0":-0.46484375,"1":0.2159423828125,"2":-0.52001953125,"3":0.2159423828125,"4":-0.46484375,"5":0.1558837890625,"6":-0.52001953125,"7":0.1558837890625},{"0":-0.470458984375,"1":0.210205078125,"2":-0.515625,"3":0.210205078125,"4":-0.470458984375,"5":0.1689453125,"6":-0.515625,"7":0.1689453125},{"0":-0.41015625,"1":0.2159423828125,"2":-0.465087890625,"3":0.2159423828125,"4":-0.41015625,"5":0.1558837890625,"6":-0.465087890625,"7":0.1558837890625},{"0":-0.41552734375,"1":0.210205078125,"2":-0.46044921875,"3":0.210205078125,"4":-0.41552734375,"5":0.1689453125,"6":-0.46044921875,"7":0.1689453125},{"0":-0.353271484375,"1":0.2159423828125,"2":-0.408203125,"3":0.2159423828125,"4":-0.353271484375,"5":0.1558837890625,"6":-0.408203125,"7":0.1558837890625},{"0":-0.358642578125,"1":0.210205078125,"2":-0.40380859375,"3":0.210205078125,"4":-0.358642578125,"5":0.1689453125,"6":-0.40380859375,"7":0.1689453125},{"0":-0.2998046875,"1":0.2159423828125,"2":-0.354736328125,"3":0.2159423828125,"4":-0.2998046875,"5":0.1558837890625,"6":-0.354736328125,"7":0.1558837890625},{"0":-0.30517578125,"1":0.210205078125,"2":-0.350341796875,"3":0.210205078125,"4":-0.30517578125,"5":0.1689453125,"6":-0.350341796875,"7":0.1689453125},{"0":-0.19091796875,"1":0.2149658203125,"2":-0.245849609375,"3":0.2149658203125,"4":-0.19091796875,"5":0.155029296875,"6":-0.245849609375,"7":0.155029296875},{"0":-0.196044921875,"1":0.2099609375,"2":-0.2410888671875,"3":0.2099609375,"4":-0.196044921875,"5":0.168701171875,"6":-0.2410888671875,"7":0.168701171875},{"0":-0.1356201171875,"1":0.2149658203125,"2":-0.1905517578125,"3":0.2149658203125,"4":-0.1356201171875,"5":0.155029296875,"6":-0.1905517578125,"7":0.155029296875},{"0":-0.1407470703125,"1":0.2099609375,"2":-0.185791015625,"3":0.2099609375,"4":-0.1407470703125,"5":0.168701171875,"6":-0.185791015625,"7":0.168701171875},{"0":-0.08026123046875,"1":0.2149658203125,"2":-0.13525390625,"3":0.2149658203125,"4":-0.08026123046875,"5":0.155029296875,"6":-0.13525390625,"7":0.155029296875},{"0":-0.08538818359375,"1":0.2099609375,"2":-0.13037109375,"3":0.2099609375,"4":-0.08538818359375,"5":0.168701171875,"6":-0.13037109375,"7":0.168701171875},{"0":-0.0249176025390625,"1":0.2159423828125,"2":-0.07989501953125,"3":0.2159423828125,"4":-0.0249176025390625,"5":0.1558837890625,"6":-0.07989501953125,"7":0.1558837890625},{"0":-0.030364990234375,"1":0.210205078125,"2":-0.07537841796875,"3":0.210205078125,"4":-0.030364990234375,"5":0.1689453125,"6":-0.07537841796875,"7":0.1689453125},{"0":0.02850341796875,"1":0.2159423828125,"2":-0.0265045166015625,"3":0.2159423828125,"4":0.02850341796875,"5":0.1558837890625,"6":-0.0265045166015625,"7":0.1558837890625},{"0":0.0230560302734375,"1":0.210205078125,"2":-0.021942138671875,"3":0.210205078125,"4":0.0230560302734375,"5":0.1689453125,"6":-0.021942138671875,"7":0.1689453125},{"0":0.0838623046875,"1":0.2159423828125,"2":0.0288848876953125,"3":0.2159423828125,"4":0.0838623046875,"5":0.1558837890625,"6":0.0288848876953125,"7":0.1558837890625},{"0":0.07843017578125,"1":0.210205078125,"2":0.033447265625,"3":0.210205078125,"4":0.07843017578125,"5":0.1689453125,"6":0.033447265625,"7":0.1689453125},{"0":0.139892578125,"1":0.2159423828125,"2":0.0848388671875,"3":0.2159423828125,"4":0.139892578125,"5":0.1558837890625,"6":0.0848388671875,"7":0.1558837890625},{"0":0.1343994140625,"1":0.210205078125,"2":0.08941650390625,"3":0.210205078125,"4":0.1343994140625,"5":0.1689453125,"6":0.08941650390625,"7":0.1689453125},{"0":0.1939697265625,"1":0.2159423828125,"2":0.138916015625,"3":0.2159423828125,"4":0.1939697265625,"5":0.1558837890625,"6":0.138916015625,"7":0.1558837890625},{"0":0.1884765625,"1":0.210205078125,"2":0.1435546875,"3":0.210205078125,"4":0.1884765625,"5":0.1689453125,"6":0.1435546875,"7":0.1689453125},{"0":0.257080078125,"1":0.2149658203125,"2":0.2021484375,"3":0.2149658203125,"4":0.257080078125,"5":0.155029296875,"6":0.2021484375,"7":0.155029296875},{"0":0.251953125,"1":0.2099609375,"2":0.20703125,"3":0.2099609375,"4":0.251953125,"5":0.168701171875,"6":0.20703125,"7":0.168701171875},{"0":0.313720703125,"1":0.2149658203125,"2":0.2587890625,"3":0.2149658203125,"4":0.313720703125,"5":0.155029296875,"6":0.2587890625,"7":0.155029296875},{"0":0.30859375,"1":0.2099609375,"2":0.263671875,"3":0.2099609375,"4":0.30859375,"5":0.168701171875,"6":0.263671875,"7":0.168701171875},{"0":0.368896484375,"1":0.2149658203125,"2":0.313720703125,"3":0.2149658203125,"4":0.368896484375,"5":0.155029296875,"6":0.313720703125,"7":0.155029296875},{"0":0.363525390625,"1":0.2099609375,"2":0.318603515625,"3":0.2099609375,"4":0.363525390625,"5":0.168701171875,"6":0.318603515625,"7":0.168701171875},{"0":0.258544921875,"1":0.162353515625,"2":0.20361328125,"3":0.162353515625,"4":0.258544921875,"5":0.1024169921875,"6":0.20361328125,"7":0.1024169921875},{"0":0.25341796875,"1":0.1573486328125,"2":0.20849609375,"3":0.1573486328125,"4":0.25341796875,"5":0.11614990234375,"6":0.20849609375,"7":0.11614990234375},{"0":0.3134765625,"1":0.162353515625,"2":0.258544921875,"3":0.162353515625,"4":0.3134765625,"5":0.1024169921875,"6":0.258544921875,"7":0.1024169921875},{"0":0.308349609375,"1":0.1573486328125,"2":0.263427734375,"3":0.1573486328125,"4":0.308349609375,"5":0.11614990234375,"6":0.263427734375,"7":0.11614990234375},{"0":0.368408203125,"1":0.162353515625,"2":0.313232421875,"3":0.162353515625,"4":0.368408203125,"5":0.1024169921875,"6":0.313232421875,"7":0.1024169921875},{"0":0.36328125,"1":0.1573486328125,"2":0.318115234375,"3":0.1573486328125,"4":0.36328125,"5":0.11614990234375,"6":0.318115234375,"7":0.11614990234375},{"0":0.257080078125,"1":0.1090087890625,"2":0.2021484375,"3":0.1090087890625,"4":0.257080078125,"5":0.048980712890625,"6":0.2021484375,"7":0.048980712890625},{"0":0.251953125,"1":0.10394287109375,"2":0.2069091796875,"3":0.10394287109375,"4":0.251953125,"5":0.062744140625,"6":0.2069091796875,"7":0.062744140625},{"0":0.3134765625,"1":0.1090087890625,"2":0.258544921875,"3":0.1090087890625,"4":0.3134765625,"5":0.048980712890625,"6":0.258544921875,"7":0.048980712890625},{"0":0.308349609375,"1":0.10394287109375,"2":0.26318359375,"3":0.10394287109375,"4":0.308349609375,"5":0.062744140625,"6":0.26318359375,"7":0.062744140625},{"0":0.369140625,"1":0.1090087890625,"2":0.31396484375,"3":0.1090087890625,"4":0.369140625,"5":0.048980712890625,"6":0.31396484375,"7":0.048980712890625},{"0":0.36376953125,"1":0.10394287109375,"2":0.31884765625,"3":0.10394287109375,"4":0.36376953125,"5":0.062744140625,"6":0.31884765625,"7":0.062744140625},{"0":0.36865234375,"1":0.1090087890625,"2":0.313720703125,"3":0.1090087890625,"4":0.36865234375,"5":0.048980712890625,"6":0.313720703125,"7":0.048980712890625},{"0":0.363525390625,"1":0.10394287109375,"2":0.318603515625,"3":0.10394287109375,"4":0.363525390625,"5":0.062744140625,"6":0.318603515625,"7":0.062744140625},{"0":0.314697265625,"1":0.003940582275390625,"2":0.259521484375,"3":0.003940582275390625,"4":0.314697265625,"5":-0.056060791015625,"6":0.259521484375,"7":-0.056060791015625},{"0":0.30908203125,"1":-0.0017843246459960938,"2":0.26416015625,"3":-0.0017843246459960938,"4":0.30908203125,"5":-0.04302978515625,"6":0.26416015625,"7":-0.04302978515625},{"0":0.313720703125,"1":-0.04962158203125,"2":0.2587890625,"3":-0.04962158203125,"4":0.313720703125,"5":-0.109619140625,"6":0.2587890625,"7":-0.109619140625},{"0":0.308349609375,"1":-0.055328369140625,"2":0.263427734375,"3":-0.055328369140625,"4":0.308349609375,"5":-0.0965576171875,"6":0.263427734375,"7":-0.0965576171875},{"0":0.25830078125,"1":-0.04962158203125,"2":0.203369140625,"3":-0.04962158203125,"4":0.25830078125,"5":-0.109619140625,"6":0.203369140625,"7":-0.109619140625},{"0":0.2529296875,"1":-0.055328369140625,"2":0.2078857421875,"3":-0.055328369140625,"4":0.2529296875,"5":-0.0965576171875,"6":0.2078857421875,"7":-0.0965576171875},{"0":0.3701171875,"1":-0.04962158203125,"2":0.315185546875,"3":-0.04962158203125,"4":0.3701171875,"5":-0.109619140625,"6":0.315185546875,"7":-0.109619140625},{"0":0.36474609375,"1":-0.055328369140625,"2":0.31982421875,"3":-0.055328369140625,"4":0.36474609375,"5":-0.0965576171875,"6":0.31982421875,"7":-0.0965576171875},{"0":0.43603515625,"1":0.2147216796875,"2":0.381103515625,"3":0.2147216796875,"4":0.43603515625,"5":0.15478515625,"6":0.381103515625,"7":0.15478515625},{"0":0.4306640625,"1":0.2091064453125,"2":0.3857421875,"3":0.2091064453125,"4":0.4306640625,"5":0.1678466796875,"6":0.3857421875,"7":0.1678466796875},{"0":0.490966796875,"1":0.2147216796875,"2":0.43603515625,"3":0.2147216796875,"4":0.490966796875,"5":0.15478515625,"6":0.43603515625,"7":0.15478515625},{"0":0.485595703125,"1":0.2091064453125,"2":0.440673828125,"3":0.2091064453125,"4":0.485595703125,"5":0.1678466796875,"6":0.440673828125,"7":0.1678466796875},{"0":0.54541015625,"1":0.2147216796875,"2":0.490234375,"3":0.2147216796875,"4":0.54541015625,"5":0.15478515625,"6":0.490234375,"7":0.15478515625},{"0":0.5400390625,"1":0.2091064453125,"2":0.494873046875,"3":0.2091064453125,"4":0.5400390625,"5":0.1678466796875,"6":0.494873046875,"7":0.1678466796875},{"0":0.6015625,"1":0.2147216796875,"2":0.54638671875,"3":0.2147216796875,"4":0.6015625,"5":0.15478515625,"6":0.54638671875,"7":0.15478515625},{"0":0.59619140625,"1":0.2091064453125,"2":0.55126953125,"3":0.2091064453125,"4":0.59619140625,"5":0.1678466796875,"6":0.55126953125,"7":0.1678466796875},{"0":0.434326171875,"1":0.162353515625,"2":0.37939453125,"3":0.162353515625,"4":0.434326171875,"5":0.1024169921875,"6":0.37939453125,"7":0.1024169921875},{"0":0.42919921875,"1":0.1573486328125,"2":0.384033203125,"3":0.1573486328125,"4":0.42919921875,"5":0.11614990234375,"6":0.384033203125,"7":0.11614990234375},{"0":0.489501953125,"1":0.162353515625,"2":0.434326171875,"3":0.162353515625,"4":0.489501953125,"5":0.1024169921875,"6":0.434326171875,"7":0.1024169921875},{"0":0.484130859375,"1":0.1573486328125,"2":0.439208984375,"3":0.1573486328125,"4":0.484130859375,"5":0.11614990234375,"6":0.439208984375,"7":0.11614990234375},{"0":0.54443359375,"1":0.162353515625,"2":0.4892578125,"3":0.162353515625,"4":0.54443359375,"5":0.1024169921875,"6":0.4892578125,"7":0.1024169921875},{"0":0.5390625,"1":0.1573486328125,"2":0.494140625,"3":0.1573486328125,"4":0.5390625,"5":0.11614990234375,"6":0.494140625,"7":0.11614990234375},{"0":0.6005859375,"1":0.162353515625,"2":0.54541015625,"3":0.162353515625,"4":0.6005859375,"5":0.1024169921875,"6":0.54541015625,"7":0.1024169921875},{"0":0.59521484375,"1":0.1573486328125,"2":0.55029296875,"3":0.1573486328125,"4":0.59521484375,"5":0.11614990234375,"6":0.55029296875,"7":0.11614990234375},{"0":0.43505859375,"1":0.10968017578125,"2":0.380126953125,"3":0.10968017578125,"4":0.43505859375,"5":0.0496826171875,"6":0.380126953125,"7":0.0496826171875},{"0":0.4296875,"1":0.10394287109375,"2":0.384521484375,"3":0.10394287109375,"4":0.4296875,"5":0.06268310546875,"6":0.384521484375,"7":0.06268310546875},{"0":0.489501953125,"1":0.10968017578125,"2":0.434326171875,"3":0.10968017578125,"4":0.489501953125,"5":0.0496826171875,"6":0.434326171875,"7":0.0496826171875},{"0":0.48388671875,"1":0.10394287109375,"2":0.43896484375,"3":0.10394287109375,"4":0.48388671875,"5":0.06268310546875,"6":0.43896484375,"7":0.06268310546875},{"0":0.54443359375,"1":0.10968017578125,"2":0.489501953125,"3":0.10968017578125,"4":0.54443359375,"5":0.0496826171875,"6":0.489501953125,"7":0.0496826171875},{"0":0.5390625,"1":0.10394287109375,"2":0.494140625,"3":0.10394287109375,"4":0.5390625,"5":0.06268310546875,"6":0.494140625,"7":0.06268310546875},{"0":0.433837890625,"1":0.056549072265625,"2":0.37890625,"3":0.056549072265625,"4":0.433837890625,"5":-0.0034618377685546875,"6":0.37890625,"7":-0.0034618377685546875},{"0":0.428466796875,"1":0.050811767578125,"2":0.383544921875,"3":0.050811767578125,"4":0.428466796875,"5":0.0095672607421875,"6":0.383544921875,"7":0.0095672607421875},{"0":0.490234375,"1":0.056549072265625,"2":0.435302734375,"3":0.056549072265625,"4":0.490234375,"5":-0.0034618377685546875,"6":0.435302734375,"7":-0.0034618377685546875},{"0":0.48486328125,"1":0.050811767578125,"2":0.439697265625,"3":0.050811767578125,"4":0.48486328125,"5":0.0095672607421875,"6":0.439697265625,"7":0.0095672607421875},{"0":0.54638671875,"1":0.056549072265625,"2":0.4912109375,"3":0.056549072265625,"4":0.54638671875,"5":-0.0034618377685546875,"6":0.4912109375,"7":-0.0034618377685546875},{"0":0.54052734375,"1":0.050811767578125,"2":0.495849609375,"3":0.050811767578125,"4":0.54052734375,"5":0.0095672607421875,"6":0.495849609375,"7":0.0095672607421875},{"0":0.433837890625,"1":0.002719879150390625,"2":0.37890625,"3":0.002719879150390625,"4":0.433837890625,"5":-0.057281494140625,"6":0.37890625,"7":-0.057281494140625},{"0":0.428466796875,"1":-0.003002166748046875,"2":0.383544921875,"3":-0.003002166748046875,"4":0.428466796875,"5":-0.04425048828125,"6":0.383544921875,"7":-0.04425048828125},{"0":0.48974609375,"1":0.002719879150390625,"2":0.4345703125,"3":0.002719879150390625,"4":0.48974609375,"5":-0.057281494140625,"6":0.4345703125,"7":-0.057281494140625},{"0":0.484130859375,"1":-0.003002166748046875,"2":0.439208984375,"3":-0.003002166748046875,"4":0.484130859375,"5":-0.04425048828125,"6":0.439208984375,"7":-0.04425048828125},{"0":0.544921875,"1":0.002719879150390625,"2":0.48974609375,"3":0.002719879150390625,"4":0.544921875,"5":-0.057281494140625,"6":0.48974609375,"7":-0.057281494140625},{"0":0.5390625,"1":-0.003002166748046875,"2":0.494384765625,"3":-0.003002166748046875,"4":0.5390625,"5":-0.04425048828125,"6":0.494384765625,"7":-0.04425048828125},{"0":0.59619140625,"1":0.107666015625,"2":0.544921875,"3":0.107666015625,"4":0.59619140625,"5":0.0026645660400390625,"6":0.544921875,"7":0.0026645660400390625},{"0":0.59423828125,"1":0.0755615234375,"2":0.54931640625,"3":0.0755615234375,"4":0.59423828125,"5":0.0343017578125,"6":0.54931640625,"7":0.0343017578125},{"0":0.457763671875,"1":-0.0572509765625,"2":0.41259765625,"3":-0.0572509765625,"4":0.457763671875,"5":-0.0985107421875,"6":0.41259765625,"7":-0.0985107421875},{"0":0.5439453125,"1":-0.0499267578125,"2":0.4892578125,"3":-0.0499267578125,"4":0.5439453125,"5":-0.10992431640625,"6":0.4892578125,"7":-0.10992431640625},{"0":0.53857421875,"1":-0.055633544921875,"2":0.49365234375,"3":-0.055633544921875,"4":0.53857421875,"5":-0.096923828125,"6":0.49365234375,"7":-0.096923828125},{"0":0.60498046875,"1":0.2225341796875,"2":-0.60498046875,"3":0.2225341796875,"4":0.60498046875,"5":-0.11126708984375,"6":-0.60498046875,"7":-0.11126708984375},{"0":-0.54638671875,"1":0.1624755859375,"2":-0.60107421875,"3":0.1624755859375,"4":-0.54638671875,"5":0.10247802734375,"6":-0.60107421875,"7":0.10247802734375},{"0":0.486328125,"1":-0.052490234375,"2":0.3798828125,"3":-0.052490234375,"4":0.486328125,"5":-0.10247802734375,"6":0.3798828125,"7":-0.10247802734375},{"0":-0.5048828125,"1":0.0574951171875,"2":-0.60107421875,"3":0.0574951171875,"4":-0.5048828125,"5":0.0025005340576171875,"6":-0.60107421875,"7":0.0025005340576171875},{"0":0.1937255859375,"1":0.0574951171875,"2":0.09747314453125,"3":0.0574951171875,"4":0.1937255859375,"5":0.0025005340576171875,"6":0.09747314453125,"7":0.0025005340576171875},{"0":-0.5185546875,"1":-0.048736572265625,"2":-0.6025390625,"3":-0.048736572265625,"4":-0.5185546875,"5":-0.10498046875,"6":-0.6025390625,"7":-0.10498046875},{"0":0.11126708984375,"1":-0.048736572265625,"2":0.042510986328125,"3":-0.048736572265625,"4":0.11126708984375,"5":-0.10498046875,"6":0.042510986328125,"7":-0.10498046875},{"0":-0.367431640625,"1":-0.048736572265625,"2":-0.452392578125,"3":-0.048736572265625,"4":-0.367431640625,"5":-0.10498046875,"6":-0.452392578125,"7":-0.10498046875},{"0":0.042510986328125,"1":-0.048736572265625,"2":-0.042510986328125,"3":-0.048736572265625,"4":0.042510986328125,"5":-0.10498046875,"6":-0.042510986328125,"7":-0.10498046875},{"0":0.1937255859375,"1":-0.04998779296875,"2":0.11126708984375,"3":-0.04998779296875,"4":0.1937255859375,"5":-0.10498046875,"6":0.11126708984375,"7":-0.10498046875},{"0":-0.452392578125,"1":-0.048736572265625,"2":-0.521484375,"3":-0.048736572265625,"4":-0.452392578125,"5":-0.10498046875,"6":-0.521484375,"7":-0.10498046875},{"0":-0.47998046875,"1":0.0025005340576171875,"2":-0.60107421875,"3":0.0025005340576171875,"4":-0.47998046875,"5":-0.0474853515625,"6":-0.60107421875,"7":-0.0474853515625},{"0":0.1925048828125,"1":0.0012502670288085938,"2":0.07122802734375,"3":0.0012502670288085938,"4":0.1925048828125,"5":-0.048736572265625,"6":0.07122802734375,"7":-0.048736572265625},{"0":0.59619140625,"1":0.0012502670288085938,"2":0.544921875,"3":0.0012502670288085938,"4":0.59619140625,"5":-0.103759765625,"6":0.544921875,"7":-0.103759765625},{"0":-0.042510986328125,"1":-0.04998779296875,"2":-0.36865234375,"3":-0.04998779296875,"4":-0.042510986328125,"5":-0.10247802734375,"6":-0.36865234375,"7":-0.10247802734375},{"0":0.197509765625,"1":0.1612548828125,"2":0.1087646484375,"3":0.1612548828125,"4":0.197509765625,"5":0.10125732421875,"6":0.1087646484375,"7":0.10125732421875},{"0":-0.2462158203125,"1":0.2149658203125,"2":-0.30126953125,"3":0.2149658203125,"4":-0.2462158203125,"5":0.155029296875,"6":-0.30126953125,"7":0.155029296875},{"0":-0.517578125,"1":0.1087646484375,"2":-0.60107421875,"3":0.1087646484375,"4":-0.517578125,"5":0.048736572265625,"6":-0.60107421875,"7":0.048736572265625},{"0":-0.5224609375,"1":0.21630859375,"2":-0.6025390625,"3":0.21630859375,"4":-0.5224609375,"5":0.15625,"6":-0.6025390625,"7":0.15625},{"0":0.59765625,"1":0.15380859375,"2":-0.59765625,"3":0.15380859375,"4":0.59765625,"5":-0.027496337890625,"6":-0.59765625,"7":-0.027496337890625}],"vertexUvs":[{"0":0.671875,"1":0.943359375,"2":0.654296875,"3":0.943359375,"4":0.671875,"5":0.92724609375,"6":0.654296875,"7":0.92724609375},{"0":0.4853515625,"1":0.587890625,"2":0.009765625,"3":0.587890625,"4":0.4853515625,"5":0.4560546875,"6":0.009765625,"7":0.4560546875},{"0":0.671875,"1":0.943359375,"2":0.654296875,"3":0.943359375,"4":0.671875,"5":0.92724609375,"6":0.654296875,"7":0.92724609375},{"0":0.62890625,"1":0.416015625,"2":0.607421875,"3":0.416015625,"4":0.62890625,"5":0.392578125,"6":0.607421875,"7":0.392578125},{"0":0.671875,"1":0.943359375,"2":0.654296875,"3":0.943359375,"4":0.671875,"5":0.92724609375,"6":0.654296875,"7":0.92724609375},{"0":0.62890625,"1":0.416015625,"2":0.607421875,"3":0.416015625,"4":0.62890625,"5":0.392578125,"6":0.607421875,"7":0.392578125},{"0":0.671875,"1":0.943359375,"2":0.654296875,"3":0.943359375,"4":0.671875,"5":0.92724609375,"6":0.654296875,"7":0.92724609375},{"0":0.62890625,"1":0.416015625,"2":0.607421875,"3":0.416015625,"4":0.62890625,"5":0.392578125,"6":0.607421875,"7":0.392578125},{"0":0.671875,"1":0.943359375,"2":0.654296875,"3":0.943359375,"4":0.671875,"5":0.92724609375,"6":0.654296875,"7":0.92724609375},{"0":0.62890625,"1":0.416015625,"2":0.607421875,"3":0.416015625,"4":0.62890625,"5":0.392578125,"6":0.607421875,"7":0.392578125},{"0":0.671875,"1":0.943359375,"2":0.654296875,"3":0.943359375,"4":0.671875,"5":0.92724609375,"6":0.654296875,"7":0.92724609375},{"0":0.62890625,"1":0.416015625,"2":0.607421875,"3":0.416015625,"4":0.62890625,"5":0.392578125,"6":0.607421875,"7":0.392578125},{"0":0.671875,"1":0.943359375,"2":0.654296875,"3":0.943359375,"4":0.671875,"5":0.92724609375,"6":0.654296875,"7":0.92724609375},{"0":0.62890625,"1":0.416015625,"2":0.607421875,"3":0.416015625,"4":0.62890625,"5":0.392578125,"6":0.607421875,"7":0.392578125},{"0":0.671875,"1":0.943359375,"2":0.654296875,"3":0.943359375,"4":0.671875,"5":0.92724609375,"6":0.654296875,"7":0.92724609375},{"0":0.62890625,"1":0.416015625,"2":0.607421875,"3":0.416015625,"4":0.62890625,"5":0.392578125,"6":0.607421875,"7":0.392578125},{"0":0.671875,"1":0.943359375,"2":0.654296875,"3":0.943359375,"4":0.671875,"5":0.92724609375,"6":0.654296875,"7":0.92724609375},{"0":0.62890625,"1":0.416015625,"2":0.607421875,"3":0.416015625,"4":0.62890625,"5":0.392578125,"6":0.607421875,"7":0.392578125},{"0":0.671875,"1":0.943359375,"2":0.654296875,"3":0.943359375,"4":0.671875,"5":0.92724609375,"6":0.654296875,"7":0.92724609375},{"0":0.62890625,"1":0.416015625,"2":0.607421875,"3":0.416015625,"4":0.62890625,"5":0.392578125,"6":0.607421875,"7":0.392578125},{"0":0.671875,"1":0.943359375,"2":0.654296875,"3":0.943359375,"4":0.671875,"5":0.92724609375,"6":0.654296875,"7":0.92724609375},{"0":0.62890625,"1":0.416015625,"2":0.607421875,"3":0.416015625,"4":0.62890625,"5":0.392578125,"6":0.607421875,"7":0.392578125},{"0":0.671875,"1":0.943359375,"2":0.654296875,"3":0.943359375,"4":0.671875,"5":0.92724609375,"6":0.654296875,"7":0.92724609375},{"0":0.62890625,"1":0.416015625,"2":0.607421875,"3":0.416015625,"4":0.62890625,"5":0.392578125,"6":0.607421875,"7":0.392578125},{"0":0.671875,"1":0.943359375,"2":0.654296875,"3":0.943359375,"4":0.671875,"5":0.92724609375,"6":0.654296875,"7":0.92724609375},{"0":0.62890625,"1":0.416015625,"2":0.607421875,"3":0.416015625,"4":0.62890625,"5":0.392578125,"6":0.607421875,"7":0.392578125},{"0":0.671875,"1":0.943359375,"2":0.654296875,"3":0.943359375,"4":0.671875,"5":0.92724609375,"6":0.654296875,"7":0.92724609375},{"0":0.671875,"1":0.943359375,"2":0.654296875,"3":0.943359375,"4":0.671875,"5":0.92724609375,"6":0.654296875,"7":0.92724609375},{"0":0.62890625,"1":0.416015625,"2":0.607421875,"3":0.416015625,"4":0.62890625,"5":0.392578125,"6":0.607421875,"7":0.392578125},{"0":0.671875,"1":0.943359375,"2":0.654296875,"3":0.943359375,"4":0.671875,"5":0.92724609375,"6":0.654296875,"7":0.92724609375},{"0":0.62890625,"1":0.416015625,"2":0.607421875,"3":0.416015625,"4":0.62890625,"5":0.392578125,"6":0.607421875,"7":0.392578125},{"0":0.671875,"1":0.943359375,"2":0.654296875,"3":0.943359375,"4":0.671875,"5":0.92724609375,"6":0.654296875,"7":0.92724609375},{"0":0.62890625,"1":0.416015625,"2":0.607421875,"3":0.416015625,"4":0.62890625,"5":0.392578125,"6":0.607421875,"7":0.392578125},{"0":0.671875,"1":0.943359375,"2":0.654296875,"3":0.943359375,"4":0.671875,"5":0.92724609375,"6":0.654296875,"7":0.92724609375},{"0":0.62890625,"1":0.416015625,"2":0.607421875,"3":0.416015625,"4":0.62890625,"5":0.392578125,"6":0.607421875,"7":0.392578125},{"0":0.671875,"1":0.943359375,"2":0.654296875,"3":0.943359375,"4":0.671875,"5":0.92724609375,"6":0.654296875,"7":0.92724609375},{"0":0.62890625,"1":0.416015625,"2":0.607421875,"3":0.416015625,"4":0.62890625,"5":0.392578125,"6":0.607421875,"7":0.392578125},{"0":0.671875,"1":0.943359375,"2":0.654296875,"3":0.943359375,"4":0.671875,"5":0.92724609375,"6":0.654296875,"7":0.92724609375},{"0":0.62890625,"1":0.416015625,"2":0.607421875,"3":0.416015625,"4":0.62890625,"5":0.392578125,"6":0.607421875,"7":0.392578125},{"0":0.671875,"1":0.943359375,"2":0.654296875,"3":0.943359375,"4":0.671875,"5":0.92724609375,"6":0.654296875,"7":0.92724609375},{"0":0.62890625,"1":0.416015625,"2":0.607421875,"3":0.416015625,"4":0.62890625,"5":0.392578125,"6":0.607421875,"7":0.392578125},{"0":0.671875,"1":0.943359375,"2":0.654296875,"3":0.943359375,"4":0.671875,"5":0.92724609375,"6":0.654296875,"7":0.92724609375},{"0":0.62890625,"1":0.416015625,"2":0.607421875,"3":0.416015625,"4":0.62890625,"5":0.392578125,"6":0.607421875,"7":0.392578125},{"0":0.671875,"1":0.943359375,"2":0.654296875,"3":0.943359375,"4":0.671875,"5":0.92724609375,"6":0.654296875,"7":0.92724609375},{"0":0.62890625,"1":0.416015625,"2":0.607421875,"3":0.416015625,"4":0.62890625,"5":0.392578125,"6":0.607421875,"7":0.392578125},{"0":0.671875,"1":0.943359375,"2":0.654296875,"3":0.943359375,"4":0.671875,"5":0.92724609375,"6":0.654296875,"7":0.92724609375},{"0":0.62890625,"1":0.416015625,"2":0.607421875,"3":0.416015625,"4":0.62890625,"5":0.392578125,"6":0.607421875,"7":0.392578125},{"0":0.671875,"1":0.943359375,"2":0.654296875,"3":0.943359375,"4":0.671875,"5":0.92724609375,"6":0.654296875,"7":0.92724609375},{"0":0.62890625,"1":0.416015625,"2":0.607421875,"3":0.416015625,"4":0.62890625,"5":0.392578125,"6":0.607421875,"7":0.392578125},{"0":0.671875,"1":0.943359375,"2":0.654296875,"3":0.943359375,"4":0.671875,"5":0.92724609375,"6":0.654296875,"7":0.92724609375},{"0":0.62890625,"1":0.416015625,"2":0.607421875,"3":0.416015625,"4":0.62890625,"5":0.392578125,"6":0.607421875,"7":0.392578125},{"0":0.671875,"1":0.943359375,"2":0.654296875,"3":0.943359375,"4":0.671875,"5":0.92724609375,"6":0.654296875,"7":0.92724609375},{"0":0.62890625,"1":0.416015625,"2":0.607421875,"3":0.416015625,"4":0.62890625,"5":0.392578125,"6":0.607421875,"7":0.392578125},{"0":0.671875,"1":0.943359375,"2":0.654296875,"3":0.943359375,"4":0.671875,"5":0.92724609375,"6":0.654296875,"7":0.92724609375},{"0":0.671875,"1":0.912109375,"2":0.654296875,"3":0.912109375,"4":0.671875,"5":0.89599609375,"6":0.654296875,"7":0.89599609375},{"0":0.671875,"1":0.912109375,"2":0.654296875,"3":0.912109375,"4":0.671875,"5":0.89599609375,"6":0.654296875,"7":0.89599609375},{"0":0.671875,"1":0.912109375,"2":0.654296875,"3":0.912109375,"4":0.671875,"5":0.89599609375,"6":0.654296875,"7":0.89599609375},{"0":0.671875,"1":0.912109375,"2":0.654296875,"3":0.912109375,"4":0.671875,"5":0.89599609375,"6":0.654296875,"7":0.89599609375},{"0":0.671875,"1":0.912109375,"2":0.654296875,"3":0.912109375,"4":0.671875,"5":0.89599609375,"6":0.654296875,"7":0.89599609375},{"0":0.671875,"1":0.912109375,"2":0.654296875,"3":0.912109375,"4":0.671875,"5":0.89599609375,"6":0.654296875,"7":0.89599609375},{"0":0.671875,"1":0.912109375,"2":0.654296875,"3":0.912109375,"4":0.671875,"5":0.89599609375,"6":0.654296875,"7":0.89599609375},{"0":0.671875,"1":0.912109375,"2":0.654296875,"3":0.912109375,"4":0.671875,"5":0.89599609375,"6":0.654296875,"7":0.89599609375},{"0":0.671875,"1":0.912109375,"2":0.654296875,"3":0.912109375,"4":0.671875,"5":0.89599609375,"6":0.654296875,"7":0.89599609375},{"0":0.671875,"1":0.912109375,"2":0.654296875,"3":0.912109375,"4":0.671875,"5":0.89599609375,"6":0.654296875,"7":0.89599609375},{"0":0.671875,"1":0.912109375,"2":0.654296875,"3":0.912109375,"4":0.671875,"5":0.89599609375,"6":0.654296875,"7":0.89599609375},{"0":0.671875,"1":0.912109375,"2":0.654296875,"3":0.912109375,"4":0.671875,"5":0.89599609375,"6":0.654296875,"7":0.89599609375},{"0":0.671875,"1":0.912109375,"2":0.654296875,"3":0.912109375,"4":0.671875,"5":0.89599609375,"6":0.654296875,"7":0.89599609375},{"0":0.671875,"1":0.912109375,"2":0.654296875,"3":0.912109375,"4":0.671875,"5":0.89599609375,"6":0.654296875,"7":0.89599609375},{"0":0.671875,"1":0.912109375,"2":0.654296875,"3":0.912109375,"4":0.671875,"5":0.89599609375,"6":0.654296875,"7":0.89599609375},{"0":0.62890625,"1":0.416015625,"2":0.607421875,"3":0.416015625,"4":0.62890625,"5":0.392578125,"6":0.607421875,"7":0.392578125},{"0":0.671875,"1":0.943359375,"2":0.654296875,"3":0.943359375,"4":0.671875,"5":0.92724609375,"6":0.654296875,"7":0.92724609375},{"0":0.62890625,"1":0.416015625,"2":0.607421875,"3":0.416015625,"4":0.62890625,"5":0.392578125,"6":0.607421875,"7":0.392578125},{"0":0.671875,"1":0.943359375,"2":0.654296875,"3":0.943359375,"4":0.671875,"5":0.92724609375,"6":0.654296875,"7":0.92724609375},{"0":0.62890625,"1":0.416015625,"2":0.607421875,"3":0.416015625,"4":0.62890625,"5":0.392578125,"6":0.607421875,"7":0.392578125},{"0":0.671875,"1":0.943359375,"2":0.654296875,"3":0.943359375,"4":0.671875,"5":0.92724609375,"6":0.654296875,"7":0.92724609375},{"0":0.62890625,"1":0.416015625,"2":0.607421875,"3":0.416015625,"4":0.62890625,"5":0.392578125,"6":0.607421875,"7":0.392578125},{"0":0.671875,"1":0.943359375,"2":0.654296875,"3":0.943359375,"4":0.671875,"5":0.92724609375,"6":0.654296875,"7":0.92724609375},{"0":0.62890625,"1":0.416015625,"2":0.607421875,"3":0.416015625,"4":0.62890625,"5":0.392578125,"6":0.607421875,"7":0.392578125},{"0":0.671875,"1":0.943359375,"2":0.654296875,"3":0.943359375,"4":0.671875,"5":0.92724609375,"6":0.654296875,"7":0.92724609375},{"0":0.62890625,"1":0.416015625,"2":0.607421875,"3":0.416015625,"4":0.62890625,"5":0.392578125,"6":0.607421875,"7":0.392578125},{"0":0.671875,"1":0.943359375,"2":0.654296875,"3":0.943359375,"4":0.671875,"5":0.92724609375,"6":0.654296875,"7":0.92724609375},{"0":0.62890625,"1":0.416015625,"2":0.607421875,"3":0.416015625,"4":0.62890625,"5":0.392578125,"6":0.607421875,"7":0.392578125},{"0":0.671875,"1":0.943359375,"2":0.654296875,"3":0.943359375,"4":0.671875,"5":0.92724609375,"6":0.654296875,"7":0.92724609375},{"0":0.62890625,"1":0.416015625,"2":0.607421875,"3":0.416015625,"4":0.62890625,"5":0.392578125,"6":0.607421875,"7":0.392578125},{"0":0.671875,"1":0.943359375,"2":0.654296875,"3":0.943359375,"4":0.671875,"5":0.92724609375,"6":0.654296875,"7":0.92724609375},{"0":0.62890625,"1":0.416015625,"2":0.607421875,"3":0.416015625,"4":0.62890625,"5":0.392578125,"6":0.607421875,"7":0.392578125},{"0":0.671875,"1":0.943359375,"2":0.654296875,"3":0.943359375,"4":0.671875,"5":0.92724609375,"6":0.654296875,"7":0.92724609375},{"0":0.62890625,"1":0.416015625,"2":0.607421875,"3":0.416015625,"4":0.62890625,"5":0.392578125,"6":0.607421875,"7":0.392578125},{"0":0.671875,"1":0.943359375,"2":0.654296875,"3":0.943359375,"4":0.671875,"5":0.92724609375,"6":0.654296875,"7":0.92724609375},{"0":0.62890625,"1":0.416015625,"2":0.607421875,"3":0.416015625,"4":0.62890625,"5":0.392578125,"6":0.607421875,"7":0.392578125},{"0":0.671875,"1":0.943359375,"2":0.654296875,"3":0.943359375,"4":0.671875,"5":0.92724609375,"6":0.654296875,"7":0.92724609375},{"0":0.62890625,"1":0.416015625,"2":0.607421875,"3":0.416015625,"4":0.62890625,"5":0.392578125,"6":0.607421875,"7":0.392578125},{"0":0.671875,"1":0.943359375,"2":0.654296875,"3":0.943359375,"4":0.671875,"5":0.92724609375,"6":0.654296875,"7":0.92724609375},{"0":0.62890625,"1":0.416015625,"2":0.607421875,"3":0.416015625,"4":0.62890625,"5":0.392578125,"6":0.607421875,"7":0.392578125},{"0":0.671875,"1":0.943359375,"2":0.654296875,"3":0.943359375,"4":0.671875,"5":0.92724609375,"6":0.654296875,"7":0.92724609375},{"0":0.62890625,"1":0.416015625,"2":0.607421875,"3":0.416015625,"4":0.62890625,"5":0.392578125,"6":0.607421875,"7":0.392578125},{"0":0.671875,"1":0.943359375,"2":0.654296875,"3":0.943359375,"4":0.671875,"5":0.92724609375,"6":0.654296875,"7":0.92724609375},{"0":0.62890625,"1":0.416015625,"2":0.607421875,"3":0.416015625,"4":0.62890625,"5":0.392578125,"6":0.607421875,"7":0.392578125},{"0":0.671875,"1":0.943359375,"2":0.654296875,"3":0.943359375,"4":0.671875,"5":0.92724609375,"6":0.654296875,"7":0.92724609375},{"0":0.62890625,"1":0.416015625,"2":0.607421875,"3":0.416015625,"4":0.62890625,"5":0.392578125,"6":0.607421875,"7":0.392578125},{"0":0.671875,"1":0.943359375,"2":0.654296875,"3":0.943359375,"4":0.671875,"5":0.92724609375,"6":0.654296875,"7":0.92724609375},{"0":0.62890625,"1":0.416015625,"2":0.607421875,"3":0.416015625,"4":0.62890625,"5":0.392578125,"6":0.607421875,"7":0.392578125},{"0":0.671875,"1":0.943359375,"2":0.654296875,"3":0.943359375,"4":0.671875,"5":0.92724609375,"6":0.654296875,"7":0.92724609375},{"0":0.62890625,"1":0.416015625,"2":0.607421875,"3":0.416015625,"4":0.62890625,"5":0.392578125,"6":0.607421875,"7":0.392578125},{"0":0.671875,"1":0.943359375,"2":0.654296875,"3":0.943359375,"4":0.671875,"5":0.92724609375,"6":0.654296875,"7":0.92724609375},{"0":0.62890625,"1":0.416015625,"2":0.607421875,"3":0.416015625,"4":0.62890625,"5":0.392578125,"6":0.607421875,"7":0.392578125},{"0":0.671875,"1":0.943359375,"2":0.654296875,"3":0.943359375,"4":0.671875,"5":0.92724609375,"6":0.654296875,"7":0.92724609375},{"0":0.62890625,"1":0.416015625,"2":0.607421875,"3":0.416015625,"4":0.62890625,"5":0.392578125,"6":0.607421875,"7":0.392578125},{"0":0.671875,"1":0.943359375,"2":0.654296875,"3":0.943359375,"4":0.671875,"5":0.92724609375,"6":0.654296875,"7":0.92724609375},{"0":0.62890625,"1":0.416015625,"2":0.607421875,"3":0.416015625,"4":0.62890625,"5":0.392578125,"6":0.607421875,"7":0.392578125},{"0":0.671875,"1":0.943359375,"2":0.654296875,"3":0.943359375,"4":0.671875,"5":0.92724609375,"6":0.654296875,"7":0.92724609375},{"0":0.62890625,"1":0.416015625,"2":0.607421875,"3":0.416015625,"4":0.62890625,"5":0.392578125,"6":0.607421875,"7":0.392578125},{"0":0.671875,"1":0.943359375,"2":0.654296875,"3":0.943359375,"4":0.671875,"5":0.92724609375,"6":0.654296875,"7":0.92724609375},{"0":0.62890625,"1":0.416015625,"2":0.607421875,"3":0.416015625,"4":0.62890625,"5":0.392578125,"6":0.607421875,"7":0.392578125},{"0":0.671875,"1":0.943359375,"2":0.654296875,"3":0.943359375,"4":0.671875,"5":0.92724609375,"6":0.654296875,"7":0.92724609375},{"0":0.62890625,"1":0.416015625,"2":0.607421875,"3":0.416015625,"4":0.62890625,"5":0.392578125,"6":0.607421875,"7":0.392578125},{"0":0.671875,"1":0.943359375,"2":0.654296875,"3":0.943359375,"4":0.671875,"5":0.92724609375,"6":0.654296875,"7":0.92724609375},{"0":0.62890625,"1":0.416015625,"2":0.607421875,"3":0.416015625,"4":0.62890625,"5":0.392578125,"6":0.607421875,"7":0.392578125},{"0":0.671875,"1":0.943359375,"2":0.654296875,"3":0.943359375,"4":0.671875,"5":0.92724609375,"6":0.654296875,"7":0.92724609375},{"0":0.666015625,"1":0.505859375,"2":0.64453125,"3":0.505859375,"4":0.666015625,"5":0.482421875,"6":0.64453125,"7":0.482421875},{"0":0.671875,"1":0.912109375,"2":0.654296875,"3":0.912109375,"4":0.671875,"5":0.89599609375,"6":0.654296875,"7":0.89599609375},{"0":0.666015625,"1":0.505859375,"2":0.64453125,"3":0.505859375,"4":0.666015625,"5":0.482421875,"6":0.64453125,"7":0.482421875},{"0":0.671875,"1":0.912109375,"2":0.654296875,"3":0.912109375,"4":0.671875,"5":0.89599609375,"6":0.654296875,"7":0.89599609375},{"0":0.666015625,"1":0.505859375,"2":0.64453125,"3":0.505859375,"4":0.666015625,"5":0.482421875,"6":0.64453125,"7":0.482421875},{"0":0.671875,"1":0.912109375,"2":0.654296875,"3":0.912109375,"4":0.671875,"5":0.89599609375,"6":0.654296875,"7":0.89599609375},{"0":0.62890625,"1":0.416015625,"2":0.607421875,"3":0.416015625,"4":0.62890625,"5":0.392578125,"6":0.607421875,"7":0.392578125},{"0":0.671875,"1":0.943359375,"2":0.654296875,"3":0.943359375,"4":0.671875,"5":0.92724609375,"6":0.654296875,"7":0.92724609375},{"0":0.62890625,"1":0.416015625,"2":0.607421875,"3":0.416015625,"4":0.62890625,"5":0.392578125,"6":0.607421875,"7":0.392578125},{"0":0.671875,"1":0.943359375,"2":0.654296875,"3":0.943359375,"4":0.671875,"5":0.92724609375,"6":0.654296875,"7":0.92724609375},{"0":0.62890625,"1":0.416015625,"2":0.607421875,"3":0.416015625,"4":0.62890625,"5":0.392578125,"6":0.607421875,"7":0.392578125},{"0":0.671875,"1":0.943359375,"2":0.654296875,"3":0.943359375,"4":0.671875,"5":0.92724609375,"6":0.654296875,"7":0.92724609375},{"0":0.62890625,"1":0.416015625,"2":0.607421875,"3":0.416015625,"4":0.62890625,"5":0.392578125,"6":0.607421875,"7":0.392578125},{"0":0.671875,"1":0.943359375,"2":0.654296875,"3":0.943359375,"4":0.671875,"5":0.92724609375,"6":0.654296875,"7":0.92724609375},{"0":0.62890625,"1":0.416015625,"2":0.607421875,"3":0.416015625,"4":0.62890625,"5":0.392578125,"6":0.607421875,"7":0.392578125},{"0":0.671875,"1":0.943359375,"2":0.654296875,"3":0.943359375,"4":0.671875,"5":0.92724609375,"6":0.654296875,"7":0.92724609375},{"0":0.666015625,"1":0.505859375,"2":0.64453125,"3":0.505859375,"4":0.666015625,"5":0.482421875,"6":0.64453125,"7":0.482421875},{"0":0.671875,"1":0.912109375,"2":0.654296875,"3":0.912109375,"4":0.671875,"5":0.89599609375,"6":0.654296875,"7":0.89599609375},{"0":0.666015625,"1":0.505859375,"2":0.64453125,"3":0.505859375,"4":0.666015625,"5":0.482421875,"6":0.64453125,"7":0.482421875},{"0":0.671875,"1":0.912109375,"2":0.654296875,"3":0.912109375,"4":0.671875,"5":0.89599609375,"6":0.654296875,"7":0.89599609375},{"0":0.666015625,"1":0.505859375,"2":0.64453125,"3":0.505859375,"4":0.666015625,"5":0.482421875,"6":0.64453125,"7":0.482421875},{"0":0.671875,"1":0.912109375,"2":0.654296875,"3":0.912109375,"4":0.671875,"5":0.89599609375,"6":0.654296875,"7":0.89599609375},{"0":0.666015625,"1":0.505859375,"2":0.64453125,"3":0.505859375,"4":0.666015625,"5":0.482421875,"6":0.64453125,"7":0.482421875},{"0":0.671875,"1":0.912109375,"2":0.654296875,"3":0.912109375,"4":0.671875,"5":0.89599609375,"6":0.654296875,"7":0.89599609375},{"0":0.666015625,"1":0.505859375,"2":0.64453125,"3":0.505859375,"4":0.666015625,"5":0.482421875,"6":0.64453125,"7":0.482421875},{"0":0.671875,"1":0.912109375,"2":0.654296875,"3":0.912109375,"4":0.671875,"5":0.89599609375,"6":0.654296875,"7":0.89599609375},{"0":0.666015625,"1":0.505859375,"2":0.64453125,"3":0.505859375,"4":0.666015625,"5":0.482421875,"6":0.64453125,"7":0.482421875},{"0":0.671875,"1":0.912109375,"2":0.654296875,"3":0.912109375,"4":0.671875,"5":0.89599609375,"6":0.654296875,"7":0.89599609375},{"0":0.666015625,"1":0.505859375,"2":0.64453125,"3":0.505859375,"4":0.666015625,"5":0.482421875,"6":0.64453125,"7":0.482421875},{"0":0.671875,"1":0.912109375,"2":0.654296875,"3":0.912109375,"4":0.671875,"5":0.89599609375,"6":0.654296875,"7":0.89599609375},{"0":0.666015625,"1":0.505859375,"2":0.64453125,"3":0.505859375,"4":0.666015625,"5":0.482421875,"6":0.64453125,"7":0.482421875},{"0":0.671875,"1":0.912109375,"2":0.654296875,"3":0.912109375,"4":0.671875,"5":0.89599609375,"6":0.654296875,"7":0.89599609375},{"0":0.666015625,"1":0.505859375,"2":0.64453125,"3":0.505859375,"4":0.666015625,"5":0.482421875,"6":0.64453125,"7":0.482421875},{"0":0.671875,"1":0.912109375,"2":0.654296875,"3":0.912109375,"4":0.671875,"5":0.89599609375,"6":0.654296875,"7":0.89599609375},{"0":0.666015625,"1":0.505859375,"2":0.64453125,"3":0.505859375,"4":0.666015625,"5":0.482421875,"6":0.64453125,"7":0.482421875},{"0":0.671875,"1":0.912109375,"2":0.654296875,"3":0.912109375,"4":0.671875,"5":0.89599609375,"6":0.654296875,"7":0.89599609375},{"0":0.62890625,"1":0.416015625,"2":0.607421875,"3":0.416015625,"4":0.62890625,"5":0.392578125,"6":0.607421875,"7":0.392578125},{"0":0.671875,"1":0.943359375,"2":0.654296875,"3":0.943359375,"4":0.671875,"5":0.92724609375,"6":0.654296875,"7":0.92724609375},{"0":0.62890625,"1":0.416015625,"2":0.607421875,"3":0.416015625,"4":0.62890625,"5":0.392578125,"6":0.607421875,"7":0.392578125},{"0":0.671875,"1":0.943359375,"2":0.654296875,"3":0.943359375,"4":0.671875,"5":0.92724609375,"6":0.654296875,"7":0.92724609375},{"0":0.62890625,"1":0.416015625,"2":0.607421875,"3":0.416015625,"4":0.62890625,"5":0.392578125,"6":0.607421875,"7":0.392578125},{"0":0.671875,"1":0.943359375,"2":0.654296875,"3":0.943359375,"4":0.671875,"5":0.92724609375,"6":0.654296875,"7":0.92724609375},{"0":0.62890625,"1":0.416015625,"2":0.607421875,"3":0.416015625,"4":0.62890625,"5":0.392578125,"6":0.607421875,"7":0.392578125},{"0":0.671875,"1":0.943359375,"2":0.654296875,"3":0.943359375,"4":0.671875,"5":0.92724609375,"6":0.654296875,"7":0.92724609375},{"0":0.62890625,"1":0.416015625,"2":0.607421875,"3":0.416015625,"4":0.62890625,"5":0.392578125,"6":0.607421875,"7":0.392578125},{"0":0.671875,"1":0.943359375,"2":0.654296875,"3":0.943359375,"4":0.671875,"5":0.92724609375,"6":0.654296875,"7":0.92724609375},{"0":0.62890625,"1":0.416015625,"2":0.607421875,"3":0.416015625,"4":0.62890625,"5":0.392578125,"6":0.607421875,"7":0.392578125},{"0":0.671875,"1":0.943359375,"2":0.654296875,"3":0.943359375,"4":0.671875,"5":0.92724609375,"6":0.654296875,"7":0.92724609375},{"0":0.62890625,"1":0.416015625,"2":0.607421875,"3":0.416015625,"4":0.62890625,"5":0.392578125,"6":0.607421875,"7":0.392578125},{"0":0.671875,"1":0.943359375,"2":0.654296875,"3":0.943359375,"4":0.671875,"5":0.92724609375,"6":0.654296875,"7":0.92724609375},{"0":0.62890625,"1":0.416015625,"2":0.607421875,"3":0.416015625,"4":0.62890625,"5":0.392578125,"6":0.607421875,"7":0.392578125},{"0":0.671875,"1":0.943359375,"2":0.654296875,"3":0.943359375,"4":0.671875,"5":0.92724609375,"6":0.654296875,"7":0.92724609375},{"0":0.666015625,"1":0.505859375,"2":0.64453125,"3":0.505859375,"4":0.666015625,"5":0.482421875,"6":0.64453125,"7":0.482421875},{"0":0.671875,"1":0.912109375,"2":0.654296875,"3":0.912109375,"4":0.671875,"5":0.89599609375,"6":0.654296875,"7":0.89599609375},{"0":0.666015625,"1":0.505859375,"2":0.64453125,"3":0.505859375,"4":0.666015625,"5":0.482421875,"6":0.64453125,"7":0.482421875},{"0":0.671875,"1":0.912109375,"2":0.654296875,"3":0.912109375,"4":0.671875,"5":0.89599609375,"6":0.654296875,"7":0.89599609375},{"0":0.666015625,"1":0.505859375,"2":0.64453125,"3":0.505859375,"4":0.666015625,"5":0.482421875,"6":0.64453125,"7":0.482421875},{"0":0.671875,"1":0.912109375,"2":0.654296875,"3":0.912109375,"4":0.671875,"5":0.89599609375,"6":0.654296875,"7":0.89599609375},{"0":0.666015625,"1":0.505859375,"2":0.64453125,"3":0.505859375,"4":0.666015625,"5":0.482421875,"6":0.64453125,"7":0.482421875},{"0":0.671875,"1":0.912109375,"2":0.654296875,"3":0.912109375,"4":0.671875,"5":0.89599609375,"6":0.654296875,"7":0.89599609375},{"0":0.62890625,"1":0.416015625,"2":0.607421875,"3":0.416015625,"4":0.62890625,"5":0.392578125,"6":0.607421875,"7":0.392578125},{"0":0.671875,"1":0.943359375,"2":0.654296875,"3":0.943359375,"4":0.671875,"5":0.92724609375,"6":0.654296875,"7":0.92724609375},{"0":0.62890625,"1":0.416015625,"2":0.607421875,"3":0.416015625,"4":0.62890625,"5":0.392578125,"6":0.607421875,"7":0.392578125},{"0":0.671875,"1":0.943359375,"2":0.654296875,"3":0.943359375,"4":0.671875,"5":0.92724609375,"6":0.654296875,"7":0.92724609375},{"0":0.62890625,"1":0.416015625,"2":0.607421875,"3":0.416015625,"4":0.62890625,"5":0.392578125,"6":0.607421875,"7":0.392578125},{"0":0.671875,"1":0.943359375,"2":0.654296875,"3":0.943359375,"4":0.671875,"5":0.92724609375,"6":0.654296875,"7":0.92724609375},{"0":0.62890625,"1":0.416015625,"2":0.607421875,"3":0.416015625,"4":0.62890625,"5":0.392578125,"6":0.607421875,"7":0.392578125},{"0":0.671875,"1":0.943359375,"2":0.654296875,"3":0.943359375,"4":0.671875,"5":0.92724609375,"6":0.654296875,"7":0.92724609375},{"0":0.62890625,"1":0.416015625,"2":0.607421875,"3":0.416015625,"4":0.62890625,"5":0.392578125,"6":0.607421875,"7":0.392578125},{"0":0.671875,"1":0.943359375,"2":0.654296875,"3":0.943359375,"4":0.671875,"5":0.92724609375,"6":0.654296875,"7":0.92724609375},{"0":0.62890625,"1":0.416015625,"2":0.607421875,"3":0.416015625,"4":0.62890625,"5":0.392578125,"6":0.607421875,"7":0.392578125},{"0":0.671875,"1":0.943359375,"2":0.654296875,"3":0.943359375,"4":0.671875,"5":0.92724609375,"6":0.654296875,"7":0.92724609375},{"0":0.62890625,"1":0.416015625,"2":0.607421875,"3":0.416015625,"4":0.62890625,"5":0.392578125,"6":0.607421875,"7":0.392578125},{"0":0.671875,"1":0.943359375,"2":0.654296875,"3":0.943359375,"4":0.671875,"5":0.92724609375,"6":0.654296875,"7":0.92724609375},{"0":0.62890625,"1":0.416015625,"2":0.607421875,"3":0.416015625,"4":0.62890625,"5":0.392578125,"6":0.607421875,"7":0.392578125},{"0":0.671875,"1":0.943359375,"2":0.654296875,"3":0.943359375,"4":0.671875,"5":0.92724609375,"6":0.654296875,"7":0.92724609375},{"0":0.62890625,"1":0.416015625,"2":0.607421875,"3":0.416015625,"4":0.62890625,"5":0.392578125,"6":0.607421875,"7":0.392578125},{"0":0.671875,"1":0.943359375,"2":0.654296875,"3":0.943359375,"4":0.671875,"5":0.92724609375,"6":0.654296875,"7":0.92724609375},{"0":0.62841796875,"1":0.505859375,"2":0.6083984375,"3":0.505859375,"4":0.62841796875,"5":0.46484375,"6":0.6083984375,"7":0.46484375},{"0":0.671875,"1":0.912109375,"2":0.654296875,"3":0.912109375,"4":0.671875,"5":0.89599609375,"6":0.654296875,"7":0.89599609375},{"0":0.671875,"1":0.943359375,"2":0.654296875,"3":0.943359375,"4":0.671875,"5":0.92724609375,"6":0.654296875,"7":0.92724609375},{"0":0.62890625,"1":0.416015625,"2":0.607421875,"3":0.416015625,"4":0.62890625,"5":0.392578125,"6":0.607421875,"7":0.392578125},{"0":0.671875,"1":0.943359375,"2":0.654296875,"3":0.943359375,"4":0.671875,"5":0.92724609375,"6":0.654296875,"7":0.92724609375},{"0":0.64013671875,"1":0.517578125,"2":0.64013671875,"3":0.990234375,"4":0.509765625,"5":0.517578125,"6":0.509765625,"7":0.990234375},{"0":0.62890625,"1":0.416015625,"2":0.607421875,"3":0.416015625,"4":0.62890625,"5":0.392578125,"6":0.607421875,"7":0.392578125},{"0":0.63671875,"1":0.447265625,"2":0.59521484375,"3":0.447265625,"4":0.63671875,"5":0.427734375,"6":0.59521484375,"7":0.427734375},{"0":0.59375,"1":0.416015625,"2":0.55615234375,"3":0.416015625,"4":0.59375,"5":0.39453125,"6":0.55615234375,"7":0.39453125},{"0":0.54052734375,"1":0.419921875,"2":0.5029296875,"3":0.419921875,"4":0.54052734375,"5":0.3984375,"6":0.5029296875,"7":0.3984375},{"0":0.67236328125,"1":0.416015625,"2":0.6396484375,"3":0.416015625,"4":0.67236328125,"5":0.39404296875,"6":0.6396484375,"7":0.39404296875},{"0":0.03662109375,"1":0.32958984375,"2":0.009765625,"3":0.32958984375,"4":0.03662109375,"5":0.3076171875,"6":0.009765625,"7":0.3076171875},{"0":0.673828125,"1":0.95703125,"2":0.673828125,"3":0.990234375,"4":0.65185546875,"5":0.95703125,"6":0.65185546875,"7":0.990234375},{"0":0.60546875,"1":0.380859375,"2":0.572265625,"3":0.380859375,"4":0.60546875,"5":0.35888671875,"6":0.572265625,"7":0.35888671875},{"0":0.6484375,"1":0.384765625,"2":0.6162109375,"3":0.384765625,"4":0.6484375,"5":0.36328125,"6":0.6162109375,"7":0.36328125},{"0":0.66943359375,"1":0.451171875,"2":0.642578125,"3":0.451171875,"4":0.66943359375,"5":0.42919921875,"6":0.642578125,"7":0.42919921875},{"0":0.5888671875,"1":0.478515625,"2":0.54150390625,"3":0.478515625,"4":0.5888671875,"5":0.458984375,"6":0.54150390625,"7":0.458984375},{"0":0.5888671875,"1":0.505859375,"2":0.54150390625,"3":0.505859375,"4":0.5888671875,"5":0.486328125,"6":0.54150390625,"7":0.486328125},{"0":0.62841796875,"1":0.505859375,"2":0.6083984375,"3":0.505859375,"4":0.62841796875,"5":0.46484375,"6":0.6083984375,"7":0.46484375},{"0":0.13720703125,"1":0.36181640625,"2":0.009765625,"3":0.36181640625,"4":0.13720703125,"5":0.34130859375,"6":0.009765625,"7":0.34130859375},{"0":0.5546875,"1":0.451171875,"2":0.52001953125,"3":0.451171875,"4":0.5546875,"5":0.427734375,"6":0.52001953125,"7":0.427734375},{"0":0.666015625,"1":0.505859375,"2":0.64453125,"3":0.505859375,"4":0.666015625,"5":0.482421875,"6":0.64453125,"7":0.482421875},{"0":0.53125,"1":0.509765625,"2":0.49853515625,"3":0.509765625,"4":0.53125,"5":0.486328125,"6":0.49853515625,"7":0.486328125},{"0":0.556640625,"1":0.384765625,"2":0.525390625,"3":0.384765625,"4":0.556640625,"5":0.361328125,"6":0.525390625,"7":0.361328125},{"0":0.4765625,"1":0.4443359375,"2":0.009765625,"3":0.4443359375,"4":0.4765625,"5":0.37353515625,"6":0.009765625,"7":0.37353515625}],"indexCounts":{"0":6,"1":6,"2":6,"3":6,"4":6,"5":6,"6":6,"7":6,"8":6,"9":6,"10":6,"11":6,"12":6,"13":6,"14":6,"15":6,"16":6,"17":6,"18":6,"19":6,"20":6,"21":6,"22":6,"23":6,"24":6,"25":6,"26":6,"27":6,"28":6,"29":6,"30":6,"31":6,"32":6,"33":6,"34":6,"35":6,"36":6,"37":6,"38":6,"39":6,"40":6,"41":6,"42":6,"43":6,"44":6,"45":6,"46":6,"47":6,"48":6,"49":6,"50":6,"51":6,"52":6,"53":6,"54":6,"55":6,"56":6,"57":6,"58":6,"59":6,"60":6,"61":6,"62":6,"63":6,"64":6,"65":6,"66":6,"67":6,"68":6,"69":6,"70":6,"71":6,"72":6,"73":6,"74":6,"75":6,"76":6,"77":6,"78":6,"79":6,"80":6,"81":6,"82":6,"83":6,"84":6,"85":6,"86":6,"87":6,"88":6,"89":6,"90":6,"91":6,"92":6,"93":6,"94":6,"95":6,"96":6,"97":6,"98":6,"99":6,"100":6,"101":6,"102":6,"103":6,"104":6,"105":6,"106":6,"107":6,"108":6,"109":6,"110":6,"111":6,"112":6,"113":6,"114":6,"115":6,"116":6,"117":6,"118":6,"119":6,"120":6,"121":6,"122":6,"123":6,"124":6,"125":6,"126":6,"127":6,"128":6,"129":6,"130":6,"131":6,"132":6,"133":6,"134":6,"135":6,"136":6,"137":6,"138":6,"139":6,"140":6,"141":6,"142":6,"143":6,"144":6,"145":6,"146":6,"147":6,"148":6,"149":6,"150":6,"151":6,"152":6,"153":6,"154":6,"155":6,"156":6,"157":6,"158":6,"159":6,"160":6,"161":6,"162":6,"163":6,"164":6,"165":6,"166":6,"167":6,"168":6,"169":6,"170":6,"171":6,"172":6,"173":6,"174":6,"175":6,"176":6,"177":6,"178":6,"179":6,"180":6,"181":6,"182":6,"183":6,"184":6,"185":6,"186":6,"187":6,"188":6,"189":6,"190":6,"191":6,"192":6,"193":6,"194":6,"195":6,"196":6,"197":6,"198":6,"199":6,"200":6,"201":6,"202":6,"203":6,"204":6,"205":6,"206":6,"207":6,"208":6,"209":6,"210":6,"211":6,"212":6,"213":6,"214":6,"215":6,"216":6,"217":6,"218":6,"219":6,"220":6,"221":6},"indices":[{"0":2,"1":0,"2":1,"3":1,"4":3,"5":2},{"0":3,"1":2,"2":0,"3":1,"4":3,"5":0},{"0":2,"1":0,"2":1,"3":1,"4":3,"5":2},{"0":2,"1":0,"2":1,"3":1,"4":3,"5":2},{"0":2,"1":0,"2":1,"3":1,"4":3,"5":2},{"0":2,"1":0,"2":1,"3":1,"4":3,"5":2},{"0":2,"1":0,"2":1,"3":1,"4":3,"5":2},{"0":2,"1":0,"2":1,"3":1,"4":3,"5":2},{"0":2,"1":0,"2":1,"3":1,"4":3,"5":2},{"0":2,"1":0,"2":1,"3":1,"4":3,"5":2},{"0":2,"1":0,"2":1,"3":1,"4":3,"5":2},{"0":2,"1":0,"2":1,"3":1,"4":3,"5":2},{"0":2,"1":0,"2":1,"3":1,"4":3,"5":2},{"0":2,"1":0,"2":1,"3":1,"4":3,"5":2},{"0":2,"1":0,"2":1,"3":1,"4":3,"5":2},{"0":2,"1":0,"2":1,"3":1,"4":3,"5":2},{"0":2,"1":0,"2":1,"3":1,"4":3,"5":2},{"0":2,"1":0,"2":1,"3":1,"4":3,"5":2},{"0":2,"1":0,"2":1,"3":1,"4":3,"5":2},{"0":2,"1":0,"2":1,"3":1,"4":3,"5":2},{"0":2,"1":0,"2":1,"3":1,"4":3,"5":2},{"0":2,"1":0,"2":1,"3":1,"4":3,"5":2},{"0":2,"1":0,"2":1,"3":1,"4":3,"5":2},{"0":2,"1":0,"2":1,"3":1,"4":3,"5":2},{"0":2,"1":0,"2":1,"3":1,"4":3,"5":2},{"0":2,"1":0,"2":1,"3":1,"4":3,"5":2},{"0":2,"1":0,"2":1,"3":1,"4":3,"5":2},{"0":2,"1":0,"2":1,"3":1,"4":3,"5":2},{"0":2,"1":0,"2":1,"3":1,"4":3,"5":2},{"0":2,"1":0,"2":1,"3":1,"4":3,"5":2},{"0":2,"1":0,"2":1,"3":1,"4":3,"5":2},{"0":2,"1":0,"2":1,"3":1,"4":3,"5":2},{"0":2,"1":0,"2":1,"3":1,"4":3,"5":2},{"0":2,"1":0,"2":1,"3":1,"4":3,"5":2},{"0":2,"1":0,"2":1,"3":1,"4":3,"5":2},{"0":2,"1":0,"2":1,"3":1,"4":3,"5":2},{"0":2,"1":0,"2":1,"3":1,"4":3,"5":2},{"0":2,"1":0,"2":1,"3":1,"4":3,"5":2},{"0":2,"1":0,"2":1,"3":1,"4":3,"5":2},{"0":2,"1":0,"2":1,"3":1,"4":3,"5":2},{"0":2,"1":0,"2":1,"3":1,"4":3,"5":2},{"0":2,"1":0,"2":1,"3":1,"4":3,"5":2},{"0":2,"1":0,"2":1,"3":1,"4":3,"5":2},{"0":2,"1":0,"2":1,"3":1,"4":3,"5":2},{"0":2,"1":0,"2":1,"3":1,"4":3,"5":2},{"0":2,"1":0,"2":1,"3":1,"4":3,"5":2},{"0":2,"1":0,"2":1,"3":1,"4":3,"5":2},{"0":2,"1":0,"2":1,"3":1,"4":3,"5":2},{"0":2,"1":0,"2":1,"3":1,"4":3,"5":2},{"0":2,"1":0,"2":1,"3":1,"4":3,"5":2},{"0":2,"1":0,"2":1,"3":1,"4":3,"5":2},{"0":2,"1":0,"2":1,"3":1,"4":3,"5":2},{"0":2,"1":0,"2":1,"3":1,"4":3,"5":2},{"0":2,"1":0,"2":1,"3":1,"4":3,"5":2},{"0":2,"1":0,"2":1,"3":1,"4":3,"5":2},{"0":2,"1":0,"2":1,"3":1,"4":3,"5":2},{"0":2,"1":0,"2":1,"3":1,"4":3,"5":2},{"0":2,"1":0,"2":1,"3":1,"4":3,"5":2},{"0":2,"1":0,"2":1,"3":1,"4":3,"5":2},{"0":2,"1":0,"2":1,"3":1,"4":3,"5":2},{"0":2,"1":0,"2":1,"3":1,"4":3,"5":2},{"0":2,"1":0,"2":1,"3":1,"4":3,"5":2},{"0":2,"1":0,"2":1,"3":1,"4":3,"5":2},{"0":2,"1":0,"2":1,"3":1,"4":3,"5":2},{"0":2,"1":0,"2":1,"3":1,"4":3,"5":2},{"0":2,"1":0,"2":1,"3":1,"4":3,"5":2},{"0":2,"1":0,"2":1,"3":1,"4":3,"5":2},{"0":2,"1":0,"2":1,"3":1,"4":3,"5":2},{"0":2,"1":0,"2":1,"3":1,"4":3,"5":2},{"0":2,"1":0,"2":1,"3":1,"4":3,"5":2},{"0":2,"1":0,"2":1,"3":1,"4":3,"5":2},{"0":2,"1":0,"2":1,"3":1,"4":3,"5":2},{"0":2,"1":0,"2":1,"3":1,"4":3,"5":2},{"0":2,"1":0,"2":1,"3":1,"4":3,"5":2},{"0":2,"1":0,"2":1,"3":1,"4":3,"5":2},{"0":2,"1":0,"2":1,"3":1,"4":3,"5":2},{"0":2,"1":0,"2":1,"3":1,"4":3,"5":2},{"0":2,"1":0,"2":1,"3":1,"4":3,"5":2},{"0":2,"1":0,"2":1,"3":1,"4":3,"5":2},{"0":2,"1":0,"2":1,"3":1,"4":3,"5":2},{"0":2,"1":0,"2":1,"3":1,"4":3,"5":2},{"0":2,"1":0,"2":1,"3":1,"4":3,"5":2},{"0":2,"1":0,"2":1,"3":1,"4":3,"5":2},{"0":2,"1":0,"2":1,"3":1,"4":3,"5":2},{"0":2,"1":0,"2":1,"3":1,"4":3,"5":2},{"0":2,"1":0,"2":1,"3":1,"4":3,"5":2},{"0":2,"1":0,"2":1,"3":1,"4":3,"5":2},{"0":2,"1":0,"2":1,"3":1,"4":3,"5":2},{"0":2,"1":0,"2":1,"3":1,"4":3,"5":2},{"0":2,"1":0,"2":1,"3":1,"4":3,"5":2},{"0":2,"1":0,"2":1,"3":1,"4":3,"5":2},{"0":2,"1":0,"2":1,"3":1,"4":3,"5":2},{"0":2,"1":0,"2":1,"3":1,"4":3,"5":2},{"0":2,"1":0,"2":1,"3":1,"4":3,"5":2},{"0":2,"1":0,"2":1,"3":1,"4":3,"5":2},{"0":2,"1":0,"2":1,"3":1,"4":3,"5":2},{"0":2,"1":0,"2":1,"3":1,"4":3,"5":2},{"0":2,"1":0,"2":1,"3":1,"4":3,"5":2},{"0":2,"1":0,"2":1,"3":1,"4":3,"5":2},{"0":2,"1":0,"2":1,"3":1,"4":3,"5":2},{"0":2,"1":0,"2":1,"3":1,"4":3,"5":2},{"0":2,"1":0,"2":1,"3":1,"4":3,"5":2},{"0":2,"1":0,"2":1,"3":1,"4":3,"5":2},{"0":2,"1":0,"2":1,"3":1,"4":3,"5":2},{"0":2,"1":0,"2":1,"3":1,"4":3,"5":2},{"0":2,"1":0,"2":1,"3":1,"4":3,"5":2},{"0":2,"1":0,"2":1,"3":1,"4":3,"5":2},{"0":2,"1":0,"2":1,"3":1,"4":3,"5":2},{"0":2,"1":0,"2":1,"3":1,"4":3,"5":2},{"0":2,"1":0,"2":1,"3":1,"4":3,"5":2},{"0":2,"1":0,"2":1,"3":1,"4":3,"5":2},{"0":2,"1":0,"2":1,"3":1,"4":3,"5":2},{"0":2,"1":0,"2":1,"3":1,"4":3,"5":2},{"0":2,"1":0,"2":1,"3":1,"4":3,"5":2},{"0":2,"1":0,"2":1,"3":1,"4":3,"5":2},{"0":2,"1":0,"2":1,"3":1,"4":3,"5":2},{"0":2,"1":0,"2":1,"3":1,"4":3,"5":2},{"0":2,"1":0,"2":1,"3":1,"4":3,"5":2},{"0":2,"1":0,"2":1,"3":1,"4":3,"5":2},{"0":2,"1":0,"2":1,"3":1,"4":3,"5":2},{"0":2,"1":0,"2":1,"3":1,"4":3,"5":2},{"0":2,"1":0,"2":1,"3":1,"4":3,"5":2},{"0":2,"1":0,"2":1,"3":1,"4":3,"5":2},{"0":2,"1":0,"2":1,"3":1,"4":3,"5":2},{"0":2,"1":0,"2":1,"3":1,"4":3,"5":2},{"0":2,"1":0,"2":1,"3":1,"4":3,"5":2},{"0":2,"1":0,"2":1,"3":1,"4":3,"5":2},{"0":2,"1":0,"2":1,"3":1,"4":3,"5":2},{"0":2,"1":0,"2":1,"3":1,"4":3,"5":2},{"0":2,"1":0,"2":1,"3":1,"4":3,"5":2},{"0":2,"1":0,"2":1,"3":1,"4":3,"5":2},{"0":2,"1":0,"2":1,"3":1,"4":3,"5":2},{"0":2,"1":0,"2":1,"3":1,"4":3,"5":2},{"0":2,"1":0,"2":1,"3":1,"4":3,"5":2},{"0":2,"1":0,"2":1,"3":1,"4":3,"5":2},{"0":2,"1":0,"2":1,"3":1,"4":3,"5":2},{"0":2,"1":0,"2":1,"3":1,"4":3,"5":2},{"0":2,"1":0,"2":1,"3":1,"4":3,"5":2},{"0":2,"1":0,"2":1,"3":1,"4":3,"5":2},{"0":2,"1":0,"2":1,"3":1,"4":3,"5":2},{"0":2,"1":0,"2":1,"3":1,"4":3,"5":2},{"0":2,"1":0,"2":1,"3":1,"4":3,"5":2},{"0":2,"1":0,"2":1,"3":1,"4":3,"5":2},{"0":2,"1":0,"2":1,"3":1,"4":3,"5":2},{"0":2,"1":0,"2":1,"3":1,"4":3,"5":2},{"0":2,"1":0,"2":1,"3":1,"4":3,"5":2},{"0":2,"1":0,"2":1,"3":1,"4":3,"5":2},{"0":2,"1":0,"2":1,"3":1,"4":3,"5":2},{"0":2,"1":0,"2":1,"3":1,"4":3,"5":2},{"0":2,"1":0,"2":1,"3":1,"4":3,"5":2},{"0":2,"1":0,"2":1,"3":1,"4":3,"5":2},{"0":2,"1":0,"2":1,"3":1,"4":3,"5":2},{"0":2,"1":0,"2":1,"3":1,"4":3,"5":2},{"0":2,"1":0,"2":1,"3":1,"4":3,"5":2},{"0":2,"1":0,"2":1,"3":1,"4":3,"5":2},{"0":2,"1":0,"2":1,"3":1,"4":3,"5":2},{"0":2,"1":0,"2":1,"3":1,"4":3,"5":2},{"0":2,"1":0,"2":1,"3":1,"4":3,"5":2},{"0":2,"1":0,"2":1,"3":1,"4":3,"5":2},{"0":2,"1":0,"2":1,"3":1,"4":3,"5":2},{"0":2,"1":0,"2":1,"3":1,"4":3,"5":2},{"0":2,"1":0,"2":1,"3":1,"4":3,"5":2},{"0":2,"1":0,"2":1,"3":1,"4":3,"5":2},{"0":2,"1":0,"2":1,"3":1,"4":3,"5":2},{"0":2,"1":0,"2":1,"3":1,"4":3,"5":2},{"0":2,"1":0,"2":1,"3":1,"4":3,"5":2},{"0":2,"1":0,"2":1,"3":1,"4":3,"5":2},{"0":2,"1":0,"2":1,"3":1,"4":3,"5":2},{"0":2,"1":0,"2":1,"3":1,"4":3,"5":2},{"0":2,"1":0,"2":1,"3":1,"4":3,"5":2},{"0":2,"1":0,"2":1,"3":1,"4":3,"5":2},{"0":2,"1":0,"2":1,"3":1,"4":3,"5":2},{"0":2,"1":0,"2":1,"3":1,"4":3,"5":2},{"0":2,"1":0,"2":1,"3":1,"4":3,"5":2},{"0":2,"1":0,"2":1,"3":1,"4":3,"5":2},{"0":2,"1":0,"2":1,"3":1,"4":3,"5":2},{"0":2,"1":0,"2":1,"3":1,"4":3,"5":2},{"0":2,"1":0,"2":1,"3":1,"4":3,"5":2},{"0":2,"1":0,"2":1,"3":1,"4":3,"5":2},{"0":2,"1":0,"2":1,"3":1,"4":3,"5":2},{"0":2,"1":0,"2":1,"3":1,"4":3,"5":2},{"0":2,"1":0,"2":1,"3":1,"4":3,"5":2},{"0":2,"1":0,"2":1,"3":1,"4":3,"5":2},{"0":2,"1":0,"2":1,"3":1,"4":3,"5":2},{"0":2,"1":0,"2":1,"3":1,"4":3,"5":2},{"0":2,"1":0,"2":1,"3":1,"4":3,"5":2},{"0":2,"1":0,"2":1,"3":1,"4":3,"5":2},{"0":2,"1":0,"2":1,"3":1,"4":3,"5":2},{"0":2,"1":0,"2":1,"3":1,"4":3,"5":2},{"0":2,"1":0,"2":1,"3":1,"4":3,"5":2},{"0":2,"1":0,"2":1,"3":1,"4":3,"5":2},{"0":2,"1":0,"2":1,"3":1,"4":3,"5":2},{"0":2,"1":0,"2":1,"3":1,"4":3,"5":2},{"0":2,"1":0,"2":1,"3":1,"4":3,"5":2},{"0":2,"1":0,"2":1,"3":1,"4":3,"5":2},{"0":2,"1":0,"2":1,"3":1,"4":3,"5":2},{"0":2,"1":0,"2":1,"3":1,"4":3,"5":2},{"0":2,"1":0,"2":1,"3":3,"4":2,"5":1},{"0":2,"1":0,"2":1,"3":1,"4":3,"5":2},{"0":2,"1":0,"2":1,"3":1,"4":3,"5":2},{"0":2,"1":0,"2":1,"3":1,"4":3,"5":2},{"0":2,"1":0,"2":1,"3":1,"4":3,"5":2},{"0":2,"1":0,"2":1,"3":1,"4":3,"5":2},{"0":2,"1":0,"2":1,"3":1,"4":3,"5":2},{"0":2,"1":0,"2":1,"3":1,"4":3,"5":2},{"0":2,"1":0,"2":1,"3":1,"4":3,"5":2},{"0":2,"1":0,"2":1,"3":1,"4":3,"5":2},{"0":2,"1":0,"2":1,"3":1,"4":3,"5":2},{"0":2,"1":0,"2":1,"3":1,"4":3,"5":2},{"0":2,"1":0,"2":1,"3":1,"4":3,"5":2},{"0":2,"1":0,"2":1,"3":1,"4":3,"5":2},{"0":2,"1":0,"2":1,"3":1,"4":3,"5":2},{"0":2,"1":0,"2":1,"3":1,"4":3,"5":2},{"0":2,"1":0,"2":1,"3":1,"4":3,"5":2},{"0":2,"1":0,"2":1,"3":1,"4":3,"5":2},{"0":2,"1":0,"2":1,"3":3,"4":2,"5":1},{"0":2,"1":0,"2":1,"3":1,"4":3,"5":2},{"0":2,"1":0,"2":1,"3":1,"4":3,"5":2},{"0":2,"1":0,"2":1,"3":1,"4":3,"5":2},{"0":2,"1":0,"2":1,"3":1,"4":3,"5":2},{"0":2,"1":0,"2":1,"3":1,"4":3,"5":2},{"0":2,"1":0,"2":1,"3":1,"4":3,"5":2}]},"canvasinfo":{"CanvasWidth":1000,"CanvasHeight":800,"CanvasOriginX":500,"CanvasOriginY":400,"PixelsPerUnit":800}}