{"code":0,"message":"0","ttl":1,"data":{"id":10035,"name":"子睿酱——模型展示","category":0,"file":"","file_data":"{\"transformData\":{},\"enableFaceTracker\":false,\"enableSettingPanel\":true}","file_size":2593647,"publish_time":1602499700000,"copyright":0,"authority":[],"tag":[{"id":33,"name":"白毛"},{"id":12,"name":"萝莉"}],"assets":[],"author_id":12248,"author_name":"子睿酱","follow_state":0,"like_count":11,"collect_count":0,"share_count":0,"state":0,"cover":"https://bimp.hdslb.com/xpeacha-pub/works/cover/33bd33c4-9ed2-4bac-977a-a6d9111dfaaa.jpg","author_avatar":"https://bimp.hdslb.com/xpeacha-pub/user/avatar/68e1b063-086e-42ed-a33a-64f05e6e0850.jpg","description":"画师：超可爱的小仙女(米画师ID)\n模型：子睿酱\n业余学习制作，会持续修改，仅作展示\n\n*优化了低头和身体前倾","comment_area_id":30,"comment_count":0,"goods_list":[],"is_like":0,"mid":0,"comment_type":42,"show_file":[],"bv_number":""}}