{"code":0,"message":"0","ttl":1,"data":{"id":10556,"name":"【有90°侧脸会走会跳的龙少女】珑沁瑶瑶","category":0,"file":"","file_data":"{\"transformData\":{},\"enableFaceTracker\":true,\"enableSettingPanel\":false}","file_size":17845550,"publish_time":1611222097000,"copyright":0,"authority":[],"tag":[{"id":261,"name":"龙少女"},{"id":12,"name":"萝莉"},{"id":103,"name":"草青"},{"id":262,"name":"雷玥云云"},{"id":191,"name":"大角度"}],"assets":[],"author_id":12619,"author_name":"草青Official","follow_state":0,"like_count":26,"collect_count":0,"share_count":0,"state":1,"cover":"https://bimp.hdslb.com/xpeacha-pub/works/cover/ef78c93a-24a6-431b-a699-e3836ef1e216.jpg","author_avatar":"https://i2.hdslb.com/bfs/face/1dccc2ecc8d7058108af3eabe8b5ca43a95ce9d3.jpg","description":"购买前请站内联系或加2011258630联系(推荐后者)，让我了解一下中之人的直播方式和频率之类的，如果中之人合适的话价格可以更低啦。\n\n————以下背景故事，中之人可以协商参考修改————\n\n------深海龙宫------\n“人族，不知要再等多少个亿年才能对话呢……唔......乏了，睡觉去”随手把手中的透镜丢在一旁，眼睛一闭，少女已然是直接睡着了\n永恒的生命，对于困居东方深海的龙少女的确过于无聊，睡觉便成了这漫长时光中最主要的活动。\n问题比较大的是...这一觉竟是从蛮荒时代睡到了……\n\n-------人界背景音：“EFE…空间站…伊莉斯”-------\n“嗯——”少女揉了揉惺忪的睡眼。\n“呜,小屃(赑屃)…我睡了多久~”她悠闲地伸了伸懒腰“什么，人类已经飞出母星了？！！”\n\n------空间站------\n“珑沁瑶瑶(人间名)申请加入，希望你们不要不识抬举~”\n“哎，这个是怎么用，啊啊啊，这个东西不亮了！”\n“什——哼…这...这这么简单的技术，我…我我一息，不对，一秒之内就能修好！”#躲起来用仙术\n\nB站展示视频：https://www.bilibili.com/video/BV1EX4y1K77C/","comment_area_id":503,"comment_count":0,"goods_list":[{"id":10035,"name":"付费下载内容","file_size":17845550,"max_stock":1,"sale_number":0,"sell_state":1,"own_state":false,"in_cart":false,"file":"","file_type":1,"price":4499,"show_file":[]}],"is_like":0,"mid":27894443,"comment_type":42,"show_file":[],"bv_number":""}}