{"code":0,"message":"0","ttl":1,"data":{"id":11028,"name":"狐茶 建模展示 魔法司机琉织酱！","category":0,"file":"","file_data":"{\"transformData\":{\"position\":{\"x\":0.031743332743644714,\"y\":-0.7344759106636047},\"scale\":{\"x\":1.3103511333465576,\"y\":1.3103511333465576}},\"enableFaceTracker\":false,\"enableSettingPanel\":false}","file_size":62681021,"publish_time":1616830596000,"copyright":0,"authority":[],"tag":[{"id":592,"name":"魔法少女"},{"id":593,"name":"巨乳"},{"id":594,"name":"歌姬"},{"id":34,"name":"粉毛"},{"id":595,"name":"高精度"}],"assets":[],"author_id":12222,"author_name":"狐茶shiroi","follow_state":0,"like_count":5,"collect_count":0,"share_count":0,"state":0,"cover":"https://bimp.hdslb.com/xpeacha-pub/works/cover/fb42ed05-4da6-41fa-a8e2-ada292fbcd88.jpg","author_avatar":"https://bimp.hdslb.com/xpeacha-pub/user/avatar/0fb68e53-1748-43ea-a6ab-c9cc6716da96.jpg","description":"狐茶正在努力学习live2D制作中~\n\n402图层+1079个变形器的高精度模型\nT4建模+9个按键表情+1个按键动作+3个按键动画\n\n中之人：北瀬琉织Channel\nb站链接：https://space.bilibili.com/650262353/\n画师：阿丫Y梓\nb站链接：https://space.bilibili.com/9941624\n建模：狐茶shrioi\nb站链接：https://space.bilibili.com/627420027\n\n【零式妖精】VUP虚拟偶像立绘建模约稿群：651305065\n狐茶QQ：943341727","comment_area_id":944,"comment_count":0,"goods_list":[],"is_like":0,"mid":0,"comment_type":42,"show_file":[],"bv_number":""}}