{"code":0,"message":"0","ttl":1,"data":{"id":11162,"name":"哼哼 Live2d模型展示-灵西","category":0,"file":"","file_data":"{\"transformData\":{},\"enableFaceTracker\":false,\"enableSettingPanel\":false}","file_size":11051702,"publish_time":1618050209000,"copyright":0,"authority":[],"tag":[{"id":7,"name":"live2d"},{"id":57,"name":"猫耳"}],"assets":[],"author_id":18280,"author_name":"哼哼_copperHHH","follow_state":0,"like_count":2,"collect_count":0,"share_count":0,"state":0,"cover":"https://bimp.hdslb.com/xpeacha-pub/works/cover/9ec9697b-effa-49f7-a5ba-285318697636.jpg","author_avatar":"https://boss.hdslb.com/xpeacha-pub/default_avatar.jpg","description":"T3精度模型，左右45度转头+上下30度转头\n中之人：灵西\n建模：哼哼\n原画：数数数数\n\nqwq因为不懂怎么在这里导出循环动画，猫尾巴会动的版本放在b站了\nb站主页：https://space.bilibili.com/12671624\n建模接单中，通常排单为一个月后，联系QQ:565752112","comment_area_id":1059,"comment_count":0,"goods_list":[],"is_like":0,"mid":0,"comment_type":42,"show_file":[],"bv_number":""}}