{"code":0,"message":"0","ttl":1,"data":{"id":11737,"name":"【live2d一条龙展示】流泪的海军猫娘","category":0,"file":"","file_data":"{\"transformData\":{},\"enableFaceTracker\":false,\"enableSettingPanel\":false}","file_size":2441536,"publish_time":1627019533000,"copyright":0,"authority":[],"tag":[{"id":18,"name":"猫娘"},{"id":7,"name":"live2d"},{"id":878,"name":"海军"},{"id":879,"name":"live2d一条龙"}],"assets":[],"author_id":36507,"author_name":"拉浮浮laff","follow_state":0,"like_count":5,"collect_count":0,"share_count":0,"state":0,"cover":"https://bimp.hdslb.com/xpeacha-pub/works/cover/4e271ec4-d3f6-452e-a0f3-e1e139926e4f.jpg","author_avatar":"https://bimp.hdslb.com/xpeacha-pub/user/avatar/512975c5-fe22-46f5-92e3-751ab2b2392a.jpg","description":"绘建都是俺\n单主是个很温柔的人\n——————————\nred为脸红红，做了下小动画，可以看一下\n以及眼睛可换色","comment_area_id":1575,"comment_count":0,"goods_list":[],"is_like":0,"mid":0,"comment_type":42,"show_file":[],"bv_number":""}}