{"code":0,"message":"0","ttl":1,"data":{"id":11815,"name":"OCLive2D——安室奈","category":0,"file":"","file_data":"{\"transformData\":{},\"enableFaceTracker\":false,\"enableSettingPanel\":false}","file_size":8510456,"publish_time":1628471468000,"copyright":0,"authority":[],"tag":[{"id":70,"name":"Live2D"},{"id":68,"name":"兽耳"},{"id":404,"name":"双马尾"},{"id":913,"name":"嘿嘿，我好了"}],"assets":[],"author_id":10279,"author_name":"RO0T_","follow_state":0,"like_count":4,"collect_count":0,"share_count":0,"state":0,"cover":"https://bimp.hdslb.com/xpeacha-pub/works/cover/c77d3e0d-336d-4348-8a86-18daa9670c07.jpg","author_avatar":"https://bimp.hdslb.com/xpeacha-pub/user/avatar/dfd17d3f-84c7-4f35-a123-c92645fc831e.jpg","description":"原画：姜可（有自己修改一些地方）\n模型：RO0T\n\n自己用的模型，直播的时候可能会套上。","comment_area_id":1648,"comment_count":0,"goods_list":[],"is_like":0,"mid":0,"comment_type":42,"show_file":[],"bv_number":""}}