{"code":0,"message":"0","ttl":1,"data":{"id":11866,"name":"【免费可商用】试做型α","category":0,"file":"","file_data":"{\"transformData\":{},\"enableFaceTracker\":true,\"enableSettingPanel\":false}","file_size":3365775,"publish_time":1629368418000,"copyright":0,"authority":[3,4,5,6],"tag":[{"id":4,"name":"免费"},{"id":269,"name":"全身"},{"id":7,"name":"live2d"},{"id":15,"name":"虚拟主播"}],"assets":[],"author_id":51137,"author_name":"食尘子","follow_state":0,"like_count":13,"collect_count":0,"share_count":0,"state":1,"cover":"https://bimp.hdslb.com/xpeacha-pub/works/cover/9806748b-d784-472d-81e7-675d72c93df2.jpg","author_avatar":"https://bimp.hdslb.com/xpeacha-pub/user/avatar/f7fa7fbf-5477-40d6-8b06-ea1052755ab4.jpg","description":"理论上来说只要不违反法律法规和平台规定的话直播出道怎么整都行\n使用的时候能标明我是作者或者b站关注我一波就更好了→b站id食尘尘尘子\n设定是等待神明【你】降临的量产伪修女←这个设定忽略也行\n其实还有修女头巾和几个表情的orz但是我太懒狗了等过段时间再整\n这个系列一共有三只。就是不知道啥时候整完【悲】\n第一次上传要是文件有问题请联系我要文档","comment_area_id":1696,"comment_count":0,"goods_list":[{"id":10209,"name":"试做型α","file_size":3365507,"max_stock":-1,"sale_number":363,"sell_state":1,"own_state":false,"in_cart":false,"file":"","file_type":1,"price":0,"show_file":[]}],"is_like":0,"mid":0,"comment_type":42,"show_file":[],"bv_number":""}}