{"code":0,"message":"0","ttl":1,"data":{"id":11916,"name":"【Live2d展示】邃紫色的少女","category":0,"file":"","file_data":"{\"transformData\":{\"position\":{\"x\":-0.00043999962508678436,\"y\":0.05329463258385658},\"scale\":{\"x\":0.9844860434532166,\"y\":0.9844860434532166}},\"enableFaceTracker\":false,\"enableSettingPanel\":false}","file_size":7262203,"publish_time":1630304830000,"copyright":0,"authority":[],"tag":[{"id":946,"name":"紫色"},{"id":152,"name":"Vtuber"},{"id":13,"name":"VUP"},{"id":56,"name":"模型"},{"id":70,"name":"Live2D"}],"assets":[],"author_id":49490,"author_name":"小丨景","follow_state":0,"like_count":27,"collect_count":0,"share_count":0,"state":0,"cover":"https://bimp.hdslb.com/xpeacha-pub/works/cover/35a62261-7727-434e-8c72-e228ff56800d.jpg","author_avatar":"https://i1.hdslb.com/bfs/face/17c73c7e3f59f8bcd3e14aa5a91b15aeb390e230.jpg","description":"UP:故巡KaTura\n画师:未确认-Sora\n模型:小丨景\n模型合作:云舒纤月\n\n欢迎约稿捏","comment_area_id":1746,"comment_count":0,"goods_list":[],"is_like":0,"mid":33943438,"comment_type":42,"show_file":[],"bv_number":""}}