{"code":0,"message":"0","ttl":1,"data":{"id":12020,"name":"live2d模型展示","category":0,"file":"","file_data":"{\"transformData\":{},\"enableFaceTracker\":false,\"enableSettingPanel\":false}","file_size":7194992,"publish_time":1632228786000,"copyright":0,"authority":[],"tag":[{"id":56,"name":"模型"},{"id":428,"name":"客单展示"},{"id":7,"name":"live2d"},{"id":265,"name":"接稿"},{"id":80,"name":"vup"}],"assets":[],"author_id":36058,"author_name":"一条余","follow_state":0,"like_count":2,"collect_count":0,"share_count":0,"state":0,"cover":"https://bimp.hdslb.com/xpeacha-pub/works/cover/dfdb8495-1e63-4f82-8ce8-65d76b451ffa.jpg","author_avatar":"https://boss.hdslb.com/xpeacha-pub/default_avatar.jpg","description":"单主：NAMI今天会交音吗\n模型：一有余地\n感谢老板给饭恰ovo\n\n广告牌：白菜接live2d虚拟形象建模 赠送简单表情按键 合作/约稿请戳企鹅：3020846236\n\n在通往大佬的路上继续努力","comment_area_id":1847,"comment_count":0,"goods_list":[],"is_like":0,"mid":0,"comment_type":42,"show_file":[],"bv_number":""}}