{"code":0,"message":"0","ttl":1,"data":{"id":12155,"name":"白鸟绫乃 半身简易模型","category":0,"file":"","file_data":"{\"transformData\":{\"position\":{\"x\":0.03720369189977646,\"y\":-0.08643027395009995},\"scale\":{\"x\":0.9040277004241943,\"y\":0.9040277004241943}},\"enableFaceTracker\":true,\"enableSettingPanel\":false}","file_size":1894987,"publish_time":1635242072000,"copyright":0,"authority":[],"tag":[],"assets":[],"author_id":12701,"author_name":"猫御daze","follow_state":0,"like_count":2,"collect_count":0,"share_count":0,"state":0,"cover":"https://bimp.hdslb.com/xpeacha-pub/works/cover/6cfae6e4-7a0d-4db7-952c-4a17a46175a3.jpg","author_avatar":"https://i0.hdslb.com/bfs/face/35814934bea810bdce898c04946feafdd9f38adb.jpg","description":"白鸟一拍脑门把约的PV图拿来让我建了个模\n立绘：言叶kisaragi\n模型：猫御daze\nvup：白鸟绫乃Official","comment_area_id":1975,"comment_count":0,"goods_list":[],"is_like":0,"mid":1402257,"comment_type":42,"show_file":[],"bv_number":""}}