{"code":0,"message":"0","ttl":1,"data":{"id":12225,"name":"可乐","category":0,"file":"","file_data":"{\"transformData\":{},\"enableFaceTracker\":false,\"enableSettingPanel\":false}","file_size":1058667,"publish_time":1636973366000,"copyright":0,"authority":[],"tag":[{"id":18,"name":"猫娘"},{"id":10,"name":"可爱"},{"id":61,"name":"女仆"}],"assets":[],"author_id":61538,"author_name":"yunr源子","follow_state":0,"like_count":8,"collect_count":0,"share_count":0,"state":0,"cover":"https://bimp.hdslb.com/xpeacha-pub/works/cover/85135f6e-e186-4711-b3bd-37cda4bfe258.jpg","author_avatar":"https://bimp.hdslb.com/xpeacha-pub/user/avatar/f943d713-e496-4968-b5a2-0237a2c2086b.jpg","description":"仅供展示","comment_area_id":2036,"comment_count":0,"goods_list":[],"is_like":0,"mid":0,"comment_type":42,"show_file":[],"bv_number":""}}