{"code":0,"message":"0","ttl":1,"data":{"id":12256,"name":"空空live2d展示","category":0,"file":"","file_data":"{\"transformData\":{\"position\":{\"x\":0.18620537221431732,\"y\":-0.1171758845448494},\"scale\":{\"x\":0.699999988079071,\"y\":0.699999988079071}},\"enableFaceTracker\":false,\"enableSettingPanel\":false}","file_size":3055648,"publish_time":1637399277000,"copyright":0,"authority":[],"tag":[],"assets":[],"author_id":62216,"author_name":"洛卡Loka","follow_state":0,"like_count":26,"collect_count":0,"share_count":0,"state":0,"cover":"https://bimp.hdslb.com/xpeacha-pub/works/cover/075a8363-dc3c-4498-bdc3-a6354a64a1f6.jpg","author_avatar":"https://i1.hdslb.com/bfs/face/267b7726562829bac37f043cb0ab49682869d981.jpg","description":"客单展示 ","comment_area_id":2060,"comment_count":0,"goods_list":[],"is_like":0,"mid":840727,"comment_type":42,"show_file":[],"bv_number":""}}