{"code":0,"message":"0","ttl":1,"data":{"id":12303,"name":"汎用ボディ【吸血鬼ちゃん】","category":0,"file":"","file_data":"{\"transformData\":{},\"enableFaceTracker\":false,\"enableSettingPanel\":false}","file_size":26613118,"publish_time":1638239612000,"copyright":1,"authority":[],"tag":[{"id":487,"name":"吸血鬼"},{"id":1039,"name":"哥特"},{"id":1040,"name":"gtloli"}],"assets":[],"author_id":64025,"author_name":"一只废阿宅在美国","follow_state":0,"like_count":25,"collect_count":0,"share_count":0,"state":0,"cover":"https://bimp.hdslb.com/xpeacha-pub/works/cover/9807178c-4012-4b92-bde2-8adb7fe55ee7.jpg","author_avatar":"https://i0.hdslb.com/bfs/face/7bab585909820ad0b7493009b4c674555f31b751.jpg","description":"已获得作者授权\n可使用建模进行直播商用\n如果有兴趣建模购买\"https://shibafooo.booth.pm/items/2946691\"\n我现在使用建模进行视频创造如果有兴趣可以 关注我 Thanks♪(･ω･)ﾉ\n对应VtubeStudio的型号。\n购买后，可以马上在VtubeStudio接受肉。\n在nizima中可以确认动作。\nhttps://nizima.com/item/detailitem/17967\n●商品详情\n・VtubeStudio用的模型数据\n・模式大小3000×6000\n・引进阿凡达和按键设定的解说\n【表情规格】\n笑容…嘴巴联动\n惊讶的脸…眉毛连动\n按键操作只有有无翅膀。\n【使用时】\n制品的商业利用是可以的，使用费也是免费的。\n这边的模型不是限定品，请谅解多人使用。\n关于使用发生的故障等，概不负责。\n【禁止事项】\n・未经许可修改制品的数据\n・制品的自作发言\n・向第三方分发制品的行为（二次分发）\n・使用制品故意给他人造成困扰的行为\n・面向成人的内容中的使用\n【关于著作权】\n没有向购买者转让著作权。\n【常见问题】\nQ：可以起新的名字吗？\nA：随便点没问题。\nQ：使用这个模型进行Vtuber活动也没问题吗？\nA：没问题。只是，请谅解多人使用这个模型进行Vtuber活动。\nQ：可以使用这个角色制作商品吗？\nA：请不要制作丙烯制品、易拉罐徽章等立体产品。\nQ：必须公开活动账号吗？\nA：哪个都没问题，但是如果能用信用卡告诉我名字的话我会很高兴的。不强制。如果在推特上有向柴生那边的告知和回复的话，请允许我把它列入吸血鬼名单。\nQ：委托第三者来画插画没问题吗？\nA:虽然委托插图没有问题，但是请不要使用吸血鬼制作新模型。\nQ：可以把这个角色委托给第三者进行3D化吗？\nA:请不要将吸血鬼3D化。\nQ：使用吸血鬼进行Vtuber活动，今后可以订购、使用新的模型吗？\nA:请不要用同样的设计制作新的作品。如果是以吸血鬼为原型设计的话，请在制作前联系DM。","comment_area_id":2096,"comment_count":0,"goods_list":[],"is_like":0,"mid":39883473,"comment_type":42,"show_file":[],"bv_number":""}}