{"code":0,"message":"0","ttl":1,"data":{"id":14456,"name":"【守护甜心】AmuletHeart已修复","category":0,"file":"","file_data":"{}","file_size":953019,"publish_time":1648560364000,"copyright":1,"authority":[],"tag":[{"id":39,"name":"Q版"},{"id":102,"name":"约稿"},{"id":70,"name":"Live2D"},{"id":466,"name":"童年"},{"id":1680,"name":"守护甜心"}],"assets":[],"author_id":62998,"author_name":"梅黧狸","follow_state":0,"like_count":59,"collect_count":0,"share_count":0,"state":0,"cover":"https://bimp.hdslb.com/xpeacha-pub/works/cover/0e6c4a86-4afa-42cc-8b93-842923e8401d.jpg","author_avatar":"https://i1.hdslb.com/bfs/face/6bb02f15de6c4b36495cc87a2ac2d8e89b816a24.jpg","description":"可用于直播以及交流学习等非商业用途，\n禁止二改！！禁止商用！！！！\n\n画师：压场鱿鱼\n建模：梅黧狸\n\n欢迎找画师约稿可爱qq人！！（画师会在小红书出没~）\n\n当时除了兰以外，还约了美琪和小丝的变身，\n虽然都是我自己花钱约的但还是考虑再三免费发放，\n也当是给画师做做宣传吧~\n\n另外两个也会抽空做出来的！嗯！（好像已经挖过好几个坑了orz）\n\n我修复了掉头bug呜呜呜呜呜呜呜","comment_area_id":3755,"comment_count":0,"goods_list":[{"id":10746,"name":"0A","file_size":960106,"max_stock":-1,"sale_number":536,"sell_state":1,"own_state":false,"in_cart":false,"file":"","file_type":1,"price":0,"show_file":[]}],"is_like":0,"mid":1491229,"comment_type":42,"show_file":[],"bv_number":""}}