{"code":0,"message":"0","ttl":1,"data":{"id":15171,"name":"【模型展示】兔兔","category":0,"file":"","file_data":"{\"enableSettingPanel\":false}","file_size":913151,"publish_time":1649763965000,"copyright":0,"authority":[],"tag":[{"id":7,"name":"live2d"},{"id":107,"name":"模型展示"}],"assets":[],"author_id":66117,"author_name":"怜同学","follow_state":0,"like_count":7,"collect_count":0,"share_count":0,"state":0,"cover":"https://bimp.hdslb.com/xpeacha-pub/works/cover/02c332dc-e251-440b-aaf1-76f82ac1b74a.jpg","author_avatar":"https://i2.hdslb.com/bfs/face/40374cc0de36a3f1682bbac07056e0692aa5996f.jpg","description":"委托人：是阿舞喔\n\n原画、建模：我","comment_area_id":4340,"comment_count":0,"goods_list":[],"is_like":0,"mid":515804,"comment_type":42,"show_file":[],"bv_number":""}}