{"code":0,"message":"0","ttl":1,"data":{"id":16436,"name":"满天星","category":0,"file":"","file_data":"{\"enableSettingPanel\":false}","file_size":161230992,"publish_time":1652776512000,"copyright":0,"authority":[],"tag":[{"id":15,"name":"虚拟主播"},{"id":101,"name":"vtuber"},{"id":80,"name":"vup"}],"assets":[],"author_id":699805,"author_name":"听涛soul","follow_state":0,"like_count":6,"collect_count":0,"share_count":0,"state":0,"cover":"https://bimp.hdslb.com/xpeacha-pub/works/cover/d8cdd66b-488c-42f0-bac5-e3f9b92b8b59.jpg","author_avatar":"https://i0.hdslb.com/bfs/face/db82abfc1e16af83ac39d93651f51207933428f0.jpg","description":"【商单】是果果！还有折腾了半天的星环动画！  https://space.bilibili.com/11999717?spm_id_from=333.337.0.0","comment_area_id":5576,"comment_count":0,"goods_list":[],"is_like":0,"mid":85169760,"comment_type":42,"show_file":[],"bv_number":""}}