{"code":0,"message":"0","ttl":1,"data":{"id":16499,"name":"橘川泷【模型展示】音乐人","category":0,"file":"","file_data":"{\"enableSettingPanel\":false}","file_size":9868223,"publish_time":1652769752000,"copyright":0,"authority":[],"tag":[{"id":7,"name":"live2d"},{"id":80,"name":"vup"},{"id":102,"name":"约稿"},{"id":116,"name":"虚拟形象"},{"id":48,"name":"展示"}],"assets":[],"author_id":27321,"author_name":"橘山颂酒","follow_state":0,"like_count":2,"collect_count":0,"share_count":0,"state":0,"cover":"https://bimp.hdslb.com/xpeacha-pub/works/cover/771be82d-a0a9-4ea1-aa8d-d2cf21266d28.jpg","author_avatar":"https://i0.hdslb.com/bfs/face/cecf836c5af8b6c0a24f4f1d48d71d38de7528b0.jpg","description":"橘川桑　live2D努力学习中\n\n画师：橘川泷\n建模：橘川泷\n\n按键表情在参数设置栏里可查看","comment_area_id":5526,"comment_count":0,"goods_list":[],"is_like":0,"mid":32382126,"comment_type":42,"show_file":[],"bv_number":""}}