{"code":0,"message":"0","ttl":1,"data":{"id":16878,"name":"Live2D模型展示","category":0,"file":"","file_data":"{\"enableSettingPanel\":true}","file_size":24049725,"publish_time":1653018700000,"copyright":0,"authority":[],"tag":[{"id":70,"name":"Live2D"},{"id":107,"name":"模型展示"},{"id":15,"name":"虚拟主播"},{"id":24,"name":"原创"}],"assets":[],"author_id":62453,"author_name":"Rewid_","follow_state":0,"like_count":4,"collect_count":0,"share_count":0,"state":0,"cover":"https://bimp.hdslb.com/xpeacha-pub/47731129-5683-4534-9253-052cdbdbfded.png","author_avatar":"https://i1.hdslb.com/bfs/face/dccdf6fb3ab37d32a728ab333a8a16cf2d704c3f.jpg","description":"春节时候的单子。\n\n接Live2d模型，有合作画师，可接一条龙。有意可b站私信或QQ1834686788。","comment_area_id":5768,"comment_count":0,"goods_list":[],"is_like":0,"mid":108765667,"comment_type":42,"show_file":[],"bv_number":""}}