{"code":0,"message":"0","ttl":1,"data":{"id":18157,"name":"异色皮精灵","category":0,"file":"","file_data":"{\"enableSettingPanel\":false}","file_size":0,"publish_time":1654500384000,"copyright":0,"authority":[4,5,6],"tag":[{"id":102,"name":"约稿"},{"id":15,"name":"虚拟主播"},{"id":105,"name":"桌宠"},{"id":80,"name":"vup"},{"id":70,"name":"Live2D"}],"assets":[],"author_id":13599,"author_name":"蓝色冰棱","follow_state":0,"like_count":10,"collect_count":0,"share_count":0,"state":0,"cover":"https://bimp.hdslb.com/xpeacha-pub/f314194e-2486-4ce4-b8cb-e4214c5e05dc.jpg","author_avatar":"https://i1.hdslb.com/bfs/face/3754e2de6c2a602d76d08cf0d18e5d321f259ab0.jpg","description":"原创合作多次售卖虚拟主播一条龙，可用于直播、桌宠、面捕、等。","comment_area_id":6822,"comment_count":0,"goods_list":[{"id":11434,"name":"异色皮精灵","file_size":18426177,"max_stock":-1,"sale_number":8,"sell_state":1,"own_state":false,"in_cart":false,"file":"","file_type":1,"price":30,"show_file":[]}],"is_like":0,"mid":109380865,"comment_type":42,"show_file":[],"bv_number":""}}