{"code":0,"message":"0","ttl":1,"data":{"id":18568,"name":"龙女自设","category":0,"file":"","file_data":"{\"enableSettingPanel\":false}","file_size":0,"publish_time":1655181838000,"copyright":0,"authority":[],"tag":[{"id":364,"name":"oc"}],"assets":[],"author_id":73783,"author_name":"每天都要白给c","follow_state":0,"like_count":2,"collect_count":0,"share_count":0,"state":0,"cover":"https://bimp.hdslb.com/xpeacha-pub/201c262e-54a6-4c49-b456-cc4442250ba9.png","author_avatar":"https://i2.hdslb.com/bfs/face/238a785a31b8a74d3766b84e91dd8bc935314377.jpg","description":"第一次做live2d，纪念一下\n有在想接一些模型制作，价格不会很高因为是新手，有想法可以 找我聊一聊哦","comment_area_id":7149,"comment_count":0,"goods_list":[],"is_like":0,"mid":241422218,"comment_type":42,"show_file":[],"bv_number":""}}