{"code":0,"message":"0","ttl":1,"data":{"id":19714,"name":"致郁思想_Channel","category":0,"file":"","file_data":"{\"enableSettingPanel\":false}","file_size":0,"publish_time":1656896890000,"copyright":0,"authority":[],"tag":[],"assets":[],"author_id":663449,"author_name":"致郁思米_Channel","follow_state":0,"like_count":20,"collect_count":0,"share_count":0,"state":0,"cover":"https://bimp.hdslb.com/xpeacha-pub/461f8d33-61ec-4fd5-aaca-3b410c66c97d.png","author_avatar":"https://i1.hdslb.com/bfs/face/4f70b6eafbe6076f15fdee363f7972f4a8f46f3b.jpg","description":"是这样的","comment_area_id":8109,"comment_count":0,"goods_list":[],"is_like":0,"mid":299892478,"comment_type":42,"show_file":[],"bv_number":""}}