{"code":0,"message":"0","ttl":1,"data":{"id":19964,"name":"乌拉の帝国Official","category":0,"file":"","file_data":"{\"enableSettingPanel\":false}","file_size":0,"publish_time":1657270655000,"copyright":0,"authority":[],"tag":[{"id":1995,"name":"游戏"},{"id":13,"name":"VUP"},{"id":3093,"name":"乌拉の帝国"}],"assets":[],"author_id":85342,"author_name":"乌拉の帝国Official","follow_state":0,"like_count":33,"collect_count":0,"share_count":0,"state":0,"cover":"https://bimp.hdslb.com/xpeacha-pub/6bebfcd7-b76d-4c33-a964-675cc2cbb8eb.jpg","author_avatar":"https://i1.hdslb.com/bfs/face/4b93d76f4af2e22ec25f5e450b98b05e27ad02e5.jpg","description":"来自宇宙的乌拉帝国帝皇，乌拉拉。","comment_area_id":8278,"comment_count":0,"goods_list":[],"is_like":0,"mid":610390,"comment_type":42,"show_file":[],"bv_number":""}}