{"code":0,"message":"0","ttl":1,"data":{"id":21161,"name":"小扁担","category":0,"file":"","file_data":"{\"enableSettingPanel\":false}","file_size":1727639,"publish_time":1660042322000,"copyright":0,"authority":[],"tag":[],"assets":[],"author_id":298830,"author_name":"我是笨蛋小扁担","follow_state":0,"like_count":4,"collect_count":0,"share_count":0,"state":0,"cover":"https://bimp.hdslb.com/xpeacha-pub/a7348a94-fcbe-4ef0-bd67-faa71fc91b25.png","author_avatar":"https://i1.hdslb.com/bfs/face/ae82bf7c62a7095c7053ab7a817298cc9b6649e9.jpg","description":"live2d 练手","comment_area_id":9258,"comment_count":0,"goods_list":[],"is_like":0,"mid":3572779,"comment_type":42,"show_file":[],"bv_number":""}}