{"code":0,"message":"0","ttl":1,"data":{"id":21725,"name":"【live2D|展示】響也喵","category":0,"file":"","file_data":"{\"enableSettingPanel\":true}","file_size":3018477,"publish_time":1661756618000,"copyright":0,"authority":[],"tag":[{"id":70,"name":"Live2D"},{"id":56,"name":"模型"},{"id":3118,"name":"無償"}],"assets":[],"author_id":66529,"author_name":"白藺瑠樺_official","follow_state":0,"like_count":3,"collect_count":0,"share_count":0,"state":0,"cover":"https://bimp.hdslb.com/xpeacha-pub/91fce101-1b6e-4fea-bcc8-b5097be01d52.png","author_avatar":"https://i0.hdslb.com/bfs/baselabs/8c2d2721d5c5629e44cdd43abdb774ba944a22fb.png","description":"響也喵\n無償\n=======================\n【展示Live2D】\n此爲單主自設展示\n\n企劃：響也喵\n畫師：Sayuri_\n建模師: 白藺瑠樺_official \n======================= \n创建了一个交流群\n关于live2D\n会分享一些基本资源\n也会根据个人喜好增加不同领域的内容\n欢迎来进行技术向的交流讨论\n========================\n群号102517397","comment_area_id":9648,"comment_count":0,"goods_list":[],"is_like":0,"mid":41871283,"comment_type":42,"show_file":[],"bv_number":""}}