{"code":0,"message":"0","ttl":1,"data":{"id":23128,"name":"可爱狐狸在线求收养！","category":0,"file":"","file_data":"{\"enableSettingPanel\":false}","file_size":19966687,"publish_time":1667359522000,"copyright":0,"authority":[3,6,5,4],"tag":[{"id":374,"name":"狐狸"},{"id":7,"name":"live2d"},{"id":80,"name":"vup"},{"id":268,"name":"皮套"},{"id":101,"name":"vtuber"}],"assets":[],"author_id":1650472,"author_name":"熙熙熙熙娜","follow_state":0,"like_count":14,"collect_count":0,"share_count":0,"state":0,"cover":"https://bimp.hdslb.com/xpeacha-pub/e82389a0-55a9-40b2-8457-7c65b0667859.png","author_avatar":"https://i0.hdslb.com/bfs/face/b078a9814d2c387fca118eef17d91fae83062baf.jpg","description":"自用不想用了，因个人原因还未出道。\n有两套衣服\n两种发色 两种眼瞳颜色\n多种表情\n有个特殊动作 撑伞\nlogo ui  op ed 界面都俱全！\n\n","comment_area_id":1,"comment_count":0,"goods_list":[{"id":12470,"name":"live2d成品模型","file_size":19966687,"max_stock":1,"sale_number":1,"sell_state":1,"own_state":false,"in_cart":false,"file":"","file_type":1,"price":4000,"show_file":[]}],"is_like":0,"mid":299388213,"comment_type":42,"show_file":[],"bv_number":""}}