{"code":0,"message":"0","ttl":1,"data":{"id":23418,"name":"海盐柠檬兔球","category":0,"file":"","file_data":"{\"enableSettingPanel\":false}","file_size":563074,"publish_time":1668745786000,"copyright":0,"authority":[6],"tag":[{"id":96,"name":"兔子"},{"id":10,"name":"可爱"},{"id":39,"name":"Q版"},{"id":7,"name":"live2d"},{"id":15,"name":"虚拟主播"}],"assets":[],"author_id":854258,"author_name":"大好青年西奈","follow_state":0,"like_count":144,"collect_count":0,"share_count":0,"state":0,"cover":"https://bimp.hdslb.com/xpeacha-pub/5cb340fb-d5a0-462a-ab1f-5713713a44a4.png","author_avatar":"https://i0.hdslb.com/bfs/face/30f1acead8d74b88a416a5926bcb063e225556f8.jpg","description":"注意事项：\n\n1. 使用的时候请标注原作者~\n2. 个人势或普通主播可以使用这个直播，直播中的收益归您自己所有。但是不可用于周边制作，参与工会，社团，企划等使用该模型进行的商业活动。\n3. 禁止盗用，二传，售卖等行为。不可以将模型说为是自己的模型。\n4. 不可用模型进行违法活动，请勿发表负面言论等，模型使用者使用模型造成的任何不良后果与模型制作者无关。\n\n感谢您的点击和喜爱~\n","comment_area_id":1,"comment_count":0,"goods_list":[{"id":12540,"name":"海盐柠檬兔球","file_size":563074,"max_stock":-1,"sale_number":5620,"sell_state":1,"own_state":false,"in_cart":false,"file":"","file_type":1,"price":0,"show_file":[]}],"is_like":0,"mid":1270215,"comment_type":42,"show_file":[],"bv_number":"BV1wR4y1f7PX"}}